Workbook

Sheet Zdroj
B1: STOCK | C1: cars | D1: managers
A2: CZ | B2: PRAHA region | C2: 1896 | D2: =VLOOKUP(B2,$M$3:$S$83,2,"nepravda") -> Petr Neckař | R2: Obsazení poboček platné od | U2: 44197
B3: PRAHA ČESTLICE | C3: 177 | D3: =VLOOKUP(B3,$M$3:$S$83,2,"nepravda") -> Pavel Saidl
B4: ÚSTÍ NAD LABEM | C4: 148 | D4: =VLOOKUP(B4,$M$3:$S$83,2,"nepravda") -> Petr Janatka | M4: Country Sales Mng. CZ | N4: Miroslav Vápeník | X4: Country Manager | Z4: Milan Dědeček | AA4: Martin Roudnický | AB4: Josef Borovec | AC4: Jan Sokola
B5: PARDUBICE | C5: 206 | D5: =VLOOKUP(B5,$M$3:$S$83,2,"nepravda") -> Roman Debkowski | N5: Site Mng. | O5: Site Mng. | P5: Site Mng. | Q5: Replace Mng. | R5: Replace Mng. | S5: Sales Closing Mng. | T5: Sales Closing Mng. | U5: Sales Closing Mng. | V5: Sales Closing Mng. | W5: Sales Closing Mng. | X5: CAP | Y5: Training | Z5: F&I Regional Mng. | AA5: Buying Regional Mng. | AB5: Stock Regional Mng. | AC5: OPS Regional Mng.
B6: ČESKÉ BUDĚJOVICE | C6: 175 | D6: =VLOOKUP(B6,$M$3:$S$83,2,"nepravda") -> Marcel Majdak | M6: PRAHA region | N6: Petr Neckař | O6: Jan Kryl | AC6: Senior Teameleader
B7: TEPLICE | C7: 143 | D7: =VLOOKUP(B7,$M$3:$S$83,2,"nepravda") -> Jan Marek | M7: Praha | N7: Jiří Hromádka | O7: Dragan Ravič | Q7: David Teplý | R7: Jakub Vavřička | S7: Richard Junger | T7: Ivan Petřík | U7: Marek Kejla | V7: Pavel Škabraha | X7: 8 | Z7: Lukáš Bělohoubek | AA7: Martin Roudnický | AB7: Martin Cmíral | AC7: Jan Malchar
B8: CHOMUTOV | C8: 187 | D8: =VLOOKUP(B8,$M$3:$S$83,2,"nepravda") -> Jan Krušina | M8: Praha Čestlice | N8: Pavel Saidl | Q8: Michal Bouček | X8: 2 | Y8: Ondřej Fencl | Z8: Lukáš Bělohoubek | AA8: Martin Roudnický | AB8: Martin Cmíral | AC8: Jan Malchar
M9: BOHEMIA 1 | N9: Miroslav Varmuža
B10: HRADEC KRÁLOVÉ | C10: 226 | D10: =VLOOKUP(B10,$M$3:$S$83,2,"nepravda") -> Martin Leš | M10: České Budějovice | N10: Marcel Majdak | Q10: Tomáš Vybíral | S10: Aleš Goszler | X10: 2 | Z10: Tomáš Vaska | AA10: Marcel Ronge | AB10: Jan Zavřel | AC10: Roman Nekola
B11: KOLÍN | C11: 145 | D11: =VLOOKUP(B11,$M$3:$S$83,2,"nepravda") -> Jiří Vojáček | M11: Chomutov | N11: Jan Krušina | Q11: Lukáš Hromádko | X11: 2 | Z11: Tomáš Vaska | AA11: Lukáš Geršic | AB11: Stanislav Bernášek | AC11: Martin Čížek
B12: JIHLAVA | C12: 156 | D12: =VLOOKUP(B12,$M$3:$S$83,2,"nepravda") -> Lukáš Prokip | M12: Kladno | N12: Ondřej Michl | Q12: Jaroslav Kříž | X12: 2 | Z12: Tomáš Vaska | AA12: Lukáš Geršic | AB12: Martin Cmíral | AC12: Martin Čížek
B13: KLADNO | C13: 188 | D13: =VLOOKUP(B13,$M$3:$S$83,2,"nepravda") -> Ondřej Michl | M13: Plzeň | N13: Jan Chadt | Q13: Stanislav Šmerda | S13: Milan Kysilka | T13: Marek Černý | X13: 4 | Z13: Tomáš Vaska | AA13: Lukáš Geršic | AB13: Martin Cmíral | AC13: Martin Čížek
B14: PLZEŇ | C14: 335 | D14: =VLOOKUP(B14,$M$3:$S$83,2,"nepravda") -> Jan Chadt | M14: Sokolov | N14: Tomáš Mrňák | Q14: Jan Kříž | X14: 2 | Z14: Tomáš Vaska | AA14: Lukáš Geršic | AB14: Stanislav Bernášek | AC14: Martin Čížek
B15: LIBEREC | C15: 291 | D15: =VLOOKUP(B15,$M$3:$S$83,2,"nepravda") -> Milan Hozák | M15: Tábor | N15: Jan Brom | Q15: David Zika | X15: 2 | Z15: Tomáš Vaska | AA15: Marcel Ronge | AB15: Jan Zavřel | AC15: Roman Nekola
B16: SOKOLOV | C16: 182 | D16: =VLOOKUP(B16,$M$3:$S$83,2,"nepravda") -> Tomáš Mrňák | M16: BOHEMIA 2 | N16: Petr Kalabis
B17: BRNO | C17: 620 | D17: =VLOOKUP(B17,$M$3:$S$83,2,"nepravda") -> Radovan Kejík | M17: Hradec Králové | N17: Martin Leš | Q17: Lukáš Uhlíř | S17: Jiří Borovička | X17: 3 | Z17: Martin Kotlán | AA17: Marcel Ronge | AB17: Jan Zavřel | AC17: Roman Nekola
B18: OTROKOVICE | C18: 219 | D18: =VLOOKUP(B18,$M$3:$S$83,2,"nepravda") -> Ondřej Polák | M18: Kolín | N18: Jiří Vojáček | Q18: Marek Bucko | X18: 2 | Z18: Martin Kotlán | AA18: Marcel Ronge | AB18: Jan Zavřel | AC18: Roman Nekola
B19: OLOMOUC | C19: 304 | D19: =VLOOKUP(B19,$M$3:$S$83,2,"nepravda") -> Tomáš Krmela | M19: Liberec | N19: Milan Hozák | Q19: David Chott | S19: Roman Martinkovič | X19: 3 | Z19: Martin Kotlán | AA19: Marcel Ronge | AB19: Stanislav Bernášek | AC19: Martin Čížek
B20: OSTRAVA | C20: 461 | D20: =VLOOKUP(B20,$M$3:$S$83,2,"nepravda") -> Marián Kozák | M20: Mladá Boleslav | N20: Petr Šulc | Q20: Matěj Šorejs | X20: 2 | Z20: Martin Kotlán | AA20: Lukáš Geršic | AB20: Stanislav Bernášek | AC20: Roman Nekola
B21: OPAVA | C21: 125 | D21: =VLOOKUP(B21,$M$3:$S$83,2,"nepravda") -> Pavel Baitl | M21: Teplice | N21: Jan Marek | Q21: Ondřej Housa | X21: 2 | Z21: Martin Kotlán | AA21: Lukáš Geršic | AB21: Stanislav Bernášek | AC21: Martin Čížek
B22: TÁBOR | C22: 92 | D22: =VLOOKUP(B22,$M$3:$S$83,2,"nepravda") -> Jan Brom | M22: Ústí nad Labem | N22: Petr Janatka | Q22: Martin Janovský | S22: Ondřej Fencl | X22: 2 | Z22: Martin Kotlán | AA22: Lukáš Geršic | AB22: Stanislav Bernášek | AC22: Martin Čížek
B23: MLADÁ BOLESLAV | C23: 149 | D23: =VLOOKUP(B23,$M$3:$S$83,2,"nepravda") -> Petr Šulc | M23: MORAVIA 1 | N23: Jiří Pokorák
B24: ZNOJMO | C24: 105 | D24: =VLOOKUP(B24,$M$3:$S$83,2,"nepravda") -> Daniel Kudr | M24: Brno | N24: Radovan Kejík | O24: Alen Svoboda | Q24: Ondřej Ištván | R24: Martin Medek | S24: Vlastimil Košťál | X24: 6 | Z24: Martin Havel | AA24: Martin Kostelka | AB24: Michal Hroch | AC24: Jan Sokola
A25: SK | B25: BRATISLAVA | C25: 452 | D25: =VLOOKUP(B25,$M$3:$S$83,2,"nepravda") -> Lukáš Špak | M25: Jihlava | N25: Lukáš Prokip | Q25: Jiří Honek | X25: 2 | Z25: Martin Havel | AA25: Marcel Ronge | AB25: Stanislav Bernášek | AC25: Roman Nekola
B26: KOŠICE | C26: 237 | D26: =VLOOKUP(B26,$M$3:$S$83,2,"nepravda") -> Lukáš Bodorík | M26: Olomouc | N26: Tomáš Krmela | Q26: Jiří Peška | S26: Kamil Martínek | T26: Jan Čechák | X26: 4 | Z26: Martin Havel | AA26: Martin Kostelka | AB26: Michal Hroch | AC26: Jan Sokola
B27: ŽILINA | C27: 171 | D27: =VLOOKUP(B27,$M$3:$S$83,2,"nepravda") -> Marek Bartík | M27: Znojmo | N27: Daniel Kudr | Q27: Josef Šimůnek | X27: 2 | Z27: Martin Havel | AA27: Martin Kostelka | AB27: Michal Hroch | AC27: Jan Sokola
B28: NITRA | C28: 169 | D28: =VLOOKUP(B28,$M$3:$S$83,2,"nepravda") -> Libor Dvořák | M28: MORAVIA 2 | N28: Jiří Vávra
B29: BÁNSKÁ BYSTRICA | C29: 172 | D29: =VLOOKUP(B29,$M$3:$S$83,2,"nepravda") -> #N/A | M29: Opava | N29: Pavel Baitl | Q29: Tomáš Hadaščok | X29: 2 | Z29: Roman Chrástecký | AA29: Martin Kostelka | AB29: Michal Hroch | AC29: Jan Sokola
B30: TRENČÍN | C30: 178 | D30: =VLOOKUP(B30,$M$3:$S$83,2,"nepravda") -> Radoslav Skaloš | M30: Ostrava | N30: Marián Kozák | O30: Miroslav Petr | Q30: Jiří Kubínek | S30: Josef Wróbel | X30: 4 | Z30: Roman Chrástecký | AA30: Martin Kostelka | AB30: Michal Hroch | AC30: Jan Sokola
B31: MICHALOVCE | C31: 100 | D31: =VLOOKUP(B31,$M$3:$S$83,2,"nepravda") -> Michal Gluchman | M31: Pardubice | N31: Roman Debkowski | Q31: Tomáš Vančura | X31: 2 | Z31: Roman Chrástecký | AA31: Marcel Ronge | AB31: Jan Zavřel | AC31: Roman Nekola
B32: POPRAD | C32: 165 | D32: =VLOOKUP(B32,$M$3:$S$83,2,"nepravda") -> Pavol Chmura | M32: Otrokovice | N32: Ondřej Polák | Q32: Tomáš Hurník | S32: Vojtěch Žák | X32: 3 | Z32: Roman Chrástecký | AA32: Martin Kostelka | AB32: Michal Hroch | AC32: Jan Sokola
B33: LUČENEC | C33: 75 | D33: =VLOOKUP(B33,$M$3:$S$83,2,"nepravda") -> Lorant Magyar | M33: Country Sales Mng. SK | N33: Igor Suchý | X33: =SUM(X7:X32) -> 63 | Z33: Lukáš Faltus | AA33: Robert Wiedner | AB33: Bronislav Kroneisl
B34: NOVÉ ZÁMKY | C34: 93 | D34: =VLOOKUP(B34,$M$3:$S$83,2,"nepravda") -> #N/A | M34: BRATISLAVA region | N34: Marek Koláček
B35: PREŠOV | C35: 172 | D35: =VLOOKUP(B35,$M$3:$S$83,2,"nepravda") -> Martin Bibko | M35: Bratislava | N35: Lukáš Špak | O35: Ľuboš Vajnagi | Q35: Štefan Stronga | Z35: Mário Záborský | AA35: Erik Droppan | AB35: Tomáš Tulej | AC35: Michal Ledvenyi
B36: MARTIN | C36: 0 | D36: =VLOOKUP(B36,$M$3:$S$83,2,"nepravda") -> #N/A | M36: Trnava | N36: Jan Tichý | Q36: Lubo Šmondrk | Z36: Martin Bulíček | AA36: Erik Droppan | AB36: Tomáš Tulej | AC36: Juraj Chrást
B37: Liptovský Mikuláš | C37: 0 | D37: =VLOOKUP(B37,$M$3:$S$83,2,"nepravda") -> #N/A | M37: SLOVAKIA 1 | N37: Lukáš Svačina
B38: TRNAVA | C38: 161 | D38: =VLOOKUP(B38,$M$3:$S$83,2,"nepravda") -> Jan Tichý | M38: Nitra | N38: Libor Dvořák | Q38: Tomáš Pytel | R38: Matěj Gál | Z38: Martin Bulíček | AA38: Erik Droppan | AB38: Tomáš Tulej | AC38: Juraj Chrást
A39: HU | B39: Budapešť | C39: 32 | D39: =VLOOKUP(B39,$M$3:$S$83,2,"nepravda") -> #N/A | M39: Trenčín | N39: Radoslav Skaloš | Q39: Richard Lehotský | Z39: Martin Bulíček | AA39: Erik Droppan | AB39: Tomáš Tulej | AC39: Juraj Chrást
A40: PL | B40: Warsaw | C40: 669 | D40: =VLOOKUP(B40,$M$3:$S$83,2,"nepravda") -> Piotr Aszychmin | M40: Žilina | N40: Marek Bartík | Q40: Roman Janoš | Z40: Martin Bulíček | AA40: Erik Droppan | AB40: Tomáš Tulej | AC40: Juraj Chrást
B41: Katowice | C41: 426 | D41: =VLOOKUP(B41,$M$3:$S$83,2,"nepravda") -> Grzegorz Imiełowski | M41: Lučenec | N41: Lorant Magyar | Q41: Norbert Molnár | Z41: Veronika Bendiková | AA41: Peter Illéš | AB41: Tomáš Tulej | AC41: Miloš Vitko
B42: Wroclaw | C42: 370 | D42: =VLOOKUP(B42,$M$3:$S$83,2,"nepravda") -> Michal Przybylski | M42: Banská Bystrica | N42: Mario Hrivnák | Q42: Michal Burda | Z42: Veronika Bendiková | AA42: Peter Illéš | AB42: Tomáš Tulej | AC42: Miloš Vitko
B43: Poznań | C43: 0 | D43: =VLOOKUP(B43,$M$3:$S$83,2,"nepravda") -> #N/A | M43: SLOVAKIA 2 | N43: Edvín Kühner
B44: Kraków | C44: 165 | D44: =VLOOKUP(B44,$M$3:$S$83,2,"nepravda") -> #N/A | M44: Košice | N44: Lukáš Bodorík | Q44: Lukáš Macháček | R44: Peter Bela | Z44: Veronika Bendiková | AA44: Peter Illéš | AB44: Tomáš Tulej | AC44: Miloš Vitko
B45: Gliwice | C45: 0 | D45: =VLOOKUP(B45,$M$3:$S$83,2,"nepravda") -> #N/A | M45: Poprad | N45: Pavol Chmura | Q45: Miloslav Michalik | Z45: Veronika Bendiková | AA45: Peter Illéš | AB45: Tomáš Tulej | AC45: Miloš Vitko
B46: Lódž | C46: 326 | D46: =VLOOKUP(B46,$M$3:$S$83,2,"nepravda") -> #N/A | M46: Michalovce | N46: Michal Gluchman | Q46: Daniel Duriak | Z46: Veronika Bendiková | AA46: Peter Illéš | AB46: Tomáš Tulej | AC46: Miloš Vitko
B47: Zabrze | C47: 199 | M47: Prešov | N47: Martin Bibko | Q47: Roland Šunda | Z47: Veronika Bendiková | AA47: Peter Illéš | AB47: Tomáš Tulej | AC47: Miloš Vitko
B48: Bielsko-Biała | C48: 2 | M48: Country Sales Mng. PL | N48: Pavel Filipi | X48: =#REF! -> #REF!
M49: Poland 1 | N49: Vít Fabián
M50: Wroclaw | N50: Michal Przybylski | O50: Vít Fabián | Q50: Aleš Tomeček | S50: Blazej Rozynski | Z50: Beata Filipi | AA50: Dariusz Snopek | AB50: David Poncza | AC50: Havlík + Jonšta
M51: Poznan
M52: Lodz | N52: Bartolomiej Zakrzewski | Q52: Lukasz Bartoszewicz | R52: Peter Kozák | Z52: Beata Filipi | AA52: Andrzej Korecki | AB52: David Poncza | AC52: Havlík + Jonšta
M53: Poland 2 | N53: Jan Lisztwan | X53: =SUM(X50:X51) -> 0
M54: Warsaw | N54: Piotr Aszychmin | O54: Jan Lisztwan | Q54: Maciej Mirkowski | S54: Ryszard Zielina | T54: Jacek Zatorski | Z54: Beata Filipi | AA54: Andrzej Korycki | AB54: David Poncza | AC54: Havlík + Jonšta
M55: Krakow
M56: Katowice | N56: Grzegorz Imiełowski | Q56: Mateusz Kijak | S56: Krzystof Ziemski | T56: Martin Rak | Z56: Beata Filipi | AA56: Dariusz Snopek | AB56: David Poncza | AC56: Havlík + Jonšta
X57: =SUM(X54:X56) -> 0
M58: Warsaw | N58: Piotr Aszychmin | O58: Jan Lisztwan | Q58: Maciej Mirkowski | S58: Ryszard Zielina | Z58: Beata Filipi | AA58: Andrzej Korycki | AB58: David Poncza | AC58: Havlík + Jonšta
M59: Krakow
M60: Katowice | N60: Grzegorz Imiełowski | Q60: Mateusz Kijak | S60: Krzystof Ziemski | T60: Martin Rak | Z60: Beata Filipi | AA60: Dariusz Snopek | AB60: David Poncza | AC60: Havlík + Jonšta
X61: =SUM(X58:X60) -> 0
X62: =SUM(X59:X61) -> 0
B81: SK | F81: BUYING SK
C82: NEW | D82: RPL | E82: TOTAL | F82: NEW | G82: RPL | H82: TOTAL | I82: Temporary
B83: BRATISLAVA HQ | C83: 2 | D83: 9 | E83: =SUM(C83:D83) -> 11 | H83: =SUM(F83:G83) -> 0
B84: BRATISLAVA | C84: 3 | D84: 9 | E84: =SUM(C84:D84) -> 12 | G84: 1 | H84: =SUM(F84:G84) -> 1
B85: ŽILINA | C85: 0 | D85: 1 | E85: =SUM(C85:D85) -> 1 | H85: =SUM(F85:G85) -> 0
B86: TRENČÍN | C86: 0 | D86: 1 | E86: =SUM(C86:D86) -> 1 | H86: =SUM(F86:G86) -> 0
B87: NITRA | E87: =SUM(C87:D87) -> 0 | G87: 0 | H87: =SUM(F87:G87) -> 0
B88: BÁNSKÁ BYSTRICA | C88: 1 | D88: 1 | E88: =SUM(C88:D88) -> 2 | G88: 0 | H88: =SUM(F88:G88) -> 0
B89: LUČENEC | E89: =SUM(C89:D89) -> 0 | G89: 0 | H89: =SUM(F89:G89) -> 0
B90: POPRAD | E90: =SUM(C90:D90) -> 0 | H90: =SUM(F90:G90) -> 0
B91: KOŠICE | C91: 0 | D91: 1 | E91: =SUM(C91:D91) -> 1 | G91: 0 | H91: =SUM(F91:G91) -> 0
B92: NOVÉ ZÁMKY | C92: 0 | D92: 0 | E92: =SUM(C92:D92) -> 0 | G92: 0 | H92: =SUM(F92:G92) -> 0
B93: PREŠOV | C93: 0 | D93: 0 | E93: =SUM(C93:D93) -> 0 | G93: 0 | H93: =SUM(F93:G93) -> 0
B94: MICHALOVCE | C94: 1 | D94: 0 | E94: =SUM(C94:D94) -> 1 | G94: 0 | H94: =SUM(F94:G94) -> 0
B95: MARTIN | C95: 0 | D95: 0 | E95: =SUM(C95:D95) -> 0 | G95: 0 | H95: =SUM(F95:G95) -> 0
B96: Liptovský Mikuláš | C96: 0 | D96: 0 | E96: =SUM(C96:D96) -> 0 | G96: 0 | H96: =SUM(F96:G96) -> 0
B97: TRNAVA | C97: 0 | D97: 0 | E97: =SUM(C97:D97) -> 0 | G97: 0 | H97: =SUM(F97:G97) -> 0
B99: HU | F99: BUYING HU
C100: NEW | D100: RPL | E100: TOTAL | F100: NEW | G100: RPL | H100: TOTAL
B101: BUDAPEST | C101: 10 | D101: 8 | E101: =SUM(C101:D101) -> 18 | F101: 1 | H101: =SUM(F101:G101) -> 1
B102: Györ | E102: =SUM(C102:D102) -> 0 | G102: 1 | H102: =SUM(F102:G102) -> 1
B103: Budaörs | E103: =SUM(C103:D103) -> 0 | F103: 1 | H103: =SUM(F103:G103) -> 1
B104: Szekesfehervár | E104: =SUM(C104:D104) -> 0 | H104: =SUM(F104:G104) -> 0
B105: SZEGED | E105: =SUM(C105:D105) -> 0 | H105: =SUM(F105:G105) -> 0
B107: PL | F107: BYUING PL
C108: NEW | D108: RPL | E108: TOTAL | F108: NEW | G108: RPL | H108: Total
A109: x | B109: PIASECZNO | C109: 7 | D109: 0 | E109: =SUM(C109:D109) -> 7 | H109: =SUM(F109:G109) -> 0
A110: x | B110: KATOWICE | C110: 5 | D110: 1 | E110: =SUM(C110:D110) -> 6 | H110: =SUM(F110:G110) -> 0
A111: x | B111: WROCŁAW | C111: 3 | D111: 4 | E111: =SUM(C111:D111) -> 7 | H111: =SUM(F111:G111) -> 0
A112: x | B112: Kraków | C112: 22 | D112: 0 | E112: =SUM(C112:D112) -> 22 | H112: =SUM(F112:G112) -> 0
B113: Lódž | C113: 0 | D113: 0 | E113: =SUM(C113:D113) -> 0 | H113: =SUM(F113:G113) -> 0 | J113: Warsava N 22, R0
A114: x | B114: Poznan | C114: 0 | D114: 4 | E114: =SUM(C114:D114) -> 4 | H114: =SUM(F114:G114) -> 0
B115: Bydgoszcz | C115: 5 | D115: 0 | E115: =SUM(C115:D115) -> 5 | H115: =SUM(F115:G115) -> 0
A116: x | B116: Gliwice | C116: 3 | D116: 0 | E116: =SUM(C116:D116) -> 3 | H116: =SUM(F116:G116) -> 0
A117: x | B117: Piastow | C117: 4 | D117: 0 | E117: =SUM(C117:D117) -> 4 | H117: =SUM(F117:G117) -> 0
D121: Praha | E121: Pobočky | F121: Buying | G121: Celkem
C122: Bára | D122: =COUNTIF(' VACANCIES'!$J$1:$J$6,"Bára") -> 0 | E122: =COUNTIF(' VACANCIES'!$J$51:$J$110,"Bára") -> 0 | F122: =COUNTIF(#REF!,"Bára") -> #REF! | G122: =SUM(D122:F122) -> #REF!
C123: Terka | D123: =COUNTIF(' VACANCIES'!$J$1:$J$6,"Terka") -> 0 | E123: =COUNTIF(' VACANCIES'!$J$51:$J$110,"Terka") -> 0 | F123: =COUNTIF(#REF!,"Terka") -> #REF! | G123: =SUM(D123:F123) -> #REF!
...

Sheet   VACANCIES
A1: Status | B1: Date of openning | C1: Time to hired | D1: Request for position | E1: Division | F1: Department | G1: Position | H1: Salary | I1: Hiring Manager | J1: Generalist | K1: Sources | L1: Comments | M1: No of CVs TOTAL | N1: CAP | O1: ACTUAL | P1: VAC
B2: TOTAL: PRAGUE HQ / BO + BRANCHES | N2: =SUM($N$3:$N$4) -> #REF! | O2: =SUM($O$3:$O$4) -> #REF! | P2: =SUM($P$3:$P$4) -> #REF!
N3: =SUM(#REF!,N50,N34) -> #REF! | O3: =SUM(#REF!,O50,O34) -> #REF! | P3: =SUM(#REF!,P50,P34,P43) -> #REF!
B4: PRAGUE HQ / BO | N4: =SUM(N5:N27) -> 195.63 | O4: =SUM(O5:O27) -> 171.14 | P4: =SUM(P5:P29) -> 37
A5: RPL (fill cap) | B5: 45782 | C5: =_xlfn.DAYS(TODAY(),B5) -> 303 | D5: 169094, 169093, 169092, | E5: 11_Call Centre | F5: CC_Ostrava | G5: CC Representative | H5: 21 000 + 0- 9 000 (1.+2.měsíc) 21 000 + %(od 3.měs.) | I5: Jan Kovář | J5: Anna K. | K5: AAA, dobra práce, práce.cz, Inwork | L5: Last hir: Blahutová, Marcol, Demeterová, Pochmanová(2.6.) No after 2nd: Marcolová (20. 3.) Kniezková (7.4.) no after 2nd: Hráčková, Jurásková, Vagáiová, | M5: 150 | N5: 51.63 | O5: 44.38 | P5: 7
A6: RPL (fill cap) | B6: 45810 | C6: =_xlfn.DAYS(TODAY(),B6) -> 275 | D6: 170489, 170490, 170491,170492, 170493 | E6: 11_Call Centre | F6: CC_Praha | G6: CC Representative | H6: 22 000 + 0- 13 000 (1.+2.měsíc) 22 000 + %(od 3.měs.) | I6: Vojta Toráč | J6: Kamila | K6: AAA, dobra práce, práce.cz, Inwork, FR | L6: Hired: Maternová, Hubačová, Vojtela ,Hiring: Nováková (1.7.), Mačáková, Šolcová (?), Bino (1.8.) no after 2nd: Křížová, Šimůnková, Švec, Bologa Didn´t come: Shonová, Tulej Refused offer: Bartáková, Skalová | M6: 68 | N6: 45 | O6: 38.76 | P6: 5 | Q6: Martin Tampír
A7: RPL (Hartlová) | B7: 45805 | C7: =_xlfn.DAYS(TODAY(),B7) -> 280 | D7: 169911 | E7: 21_Commerce | F7: Import & Export | G7: Assistant | H7: 25.000 + 0 - 25.000 KPI | I7: Robert Radler | J7: Ondra | K7: AAA, práce | L7: Hired Kmochová For 2nd Krásnová, Havlíčková | M7: 11 | N7: 4 | O7: 4 | P7: 1
A8: RPL (Gamazova) | B8: 45786 | C8: =_xlfn.DAYS(TODAY(),B8) -> 299 | D8: 168637 | E8: 01_Marketing & Communication | F8: Web and Direct Marketing | G8: Web Specialist | H8: negotiable | I8: Martin Tampír | J8: Ondra | K8: AAA, jobs, LI, Profesia | L8: In considering Suská No after phonescreen 4x Checking CVs | M8: 5 | N8: 2 | O8: 2 | P8: 1
A9: RPL (Polcar) | B9: 45789 | C9: =_xlfn.DAYS(TODAY(),B9) -> 296 | D9: 168789 | E9: 01_Marketing & Communication | F9: Digital Marketing | G9: Online Marketing Specialist | H9: negotiable | I9: Karel Smrž | J9: Anička | K9: AAA, jobs, práce.cz, LI | L9: Checking CV's No after 2nd Šuťák | M9: 5 | N9: 1 | O9: 1 | P9: 1
A10: RPL (Šubrt) + NEW | B10: 45789 | C10: =_xlfn.DAYS(TODAY(),B10) -> 296 | D10: 168935 | E10: 01_Marketing & Communication | F10: Brand Design | G10: Graphic | H10: negotiable | I10: Karel Smrž | J10: Anička | K10: AAA, jobs, práce.cz, LI | L10: Hiring Vašíčková, Procházka (16.6) Got offer for external cooperation Melanikova Case study Střelec, Svoboda, Mihal No after 2nd Ranc, Gabriel, Tvrz, Povolný, Brna, Baldina, Gobunov, Pícha | M10: 0 | N10: 2 | O10: 2 | P10: 2
A11: NEW CAP | B11: 45818 | C11: =_xlfn.DAYS(TODAY(),B11) -> 267 | D11: Waiting for RFP | E11: 01_Marketing & Communication | F11: Brand Design | G11: DTP/Graphic | H11: negotiable | I11: Jan Metelka | J11: Anička | K11: AAA, jobs, práce.cz, LI | L11: New request | M11: 0 | N11: 1 | O11: 1 | P11: 1
A12: RPL (Kappel) | B12: 45751 | C12: =_xlfn.DAYS(TODAY(),B12) -> 334 | D12: 170526 | E12: 04_Economic | F12: Consolidation & Projects | G12: Group Tax Manager | H12: negotiable | I12: Vojtěch Karban | J12: Anička | K12: AAA, jobs, LI, FR | L12: Msg sent 25x Refused practice test Malina Not responding Skalický No after psc Hýža | M12: 3 | N12: 1 | O12: 1 | P12: 1
A13: RPL (Kočová) | B13: 45784 | C13: =_xlfn.DAYS(TODAY(),B13) -> 301 | D13: 168872 | E13: 04_Economic | F13: Consolidation & Projects | G13: IFRS Specialist | H13: negotiable | I13: Martin Přibyl | J13: Anička | K13: AAA, jobs, LI, FR | L13: For 2nd Papanov (4.6) Good for psc Němeček Not interested Beránková Overpriced Ustianskyi | M13: 2 | N13: 2 | O13: 2 | P13: 1
A14: RPL (Kralovičová) | B14: 45720 | C14: =_xlfn.DAYS(TODAY(),B14) -> 365 | D14: 165269 | E14: 06_HR | F14: Personnel&Payroll | G14: Payroll Accountant | H14: negotiable | I14: Jitka Hořejší | J14: Ondra | K14: AAA, Jobs, intersource, ATS search | L14: Hired 23.6. Havelková | M14: 6 | N14: 4 | O14: 4 | P14: 1
A15: RPL (Jurštak) | B15: 45796 | C15: =_xlfn.DAYS(TODAY(),B15) -> 289 | D15: 168877 | E15: 06_HR | F15: Personnel&Payroll | G15: HR Controller | H15: negotiable Ref. | I15: Martina Kahulová | J15: Vlaďka | K15: intersource, ATS search | L15: got offer Zajícová, after 1 st internal candidate | M15: 2 | N15: 1 | O15: 1 | P15: 1
A16: RPL (Vojtíšek) | B16: 45757 | C16: =_xlfn.DAYS(TODAY(),B16) -> 328 | D16: 167036 | E16: 12_IT | F16: IT Development | G16: Project Manger | H16: negotiable | I16: Robert Šmol | J16: Ondra | K16: AAA, jobs, LI | L16: Hiring Havrylova | M16: 2 | N16: 1 | O16: 1 | P16: 1
A17: RPL (Jurčík) | B17: 45733 | C17: =_xlfn.DAYS(TODAY(),B17) -> 352 | D17: 154897 | E17: 08_Service | F17: Service | G17: Mechanic / Brno | H17: negotiable Ref. Náb.příspěvek | I17: Miroslav Knap | J17: Honza | K17: AAA, jobdnes, volnamista,facebook, dobrá práce, práce cz,inwork | L17: Checking CVs Hired Kosek (17.3.), Plaček (4.3.) Refused offer Brezánsky No after 1st Huspenina, Sokol, Kopecký, Hošek (not suitable), Lavička, Čamek (didnt start), Šlehofer (didnt come) | M17: 16 | N17: 8 | O17: 7 | P17: 1
A18: RPL (Válek) | B18: 45733 | C18: =_xlfn.DAYS(TODAY(),B18) -> 352 | D18: 140136 | E18: 08_Service | F18: Service | G18: Mechanic / Praha | H18: negotiable Ref. | I18: Miroslav Knap | J18: Honza | K18: AAA, jobdnes, volnamista,facebook, dobrá práce, práce cz,inwork | L18: Checking CVs | M18: 5 | N18: 22 | O18: 21 | P18: 1
A19: RPL (Hlavatý) | B19: 45803 | C19: =_xlfn.DAYS(TODAY(),B19) -> 282 | D19: 169604 | E19: 08_Service | F19: Service | G19: Mechanic / Hradec Králové | H19: negotiable Ref. | I19: Miroslav Knap | J19: Honza | K19: AAA, jobdnes, volnamista,facebook, dobrá práce, práce cz,inwork | L19: New request | M19: 1 | N19: 2 | O19: 2 | P19: 1
A20: RPL (Beck) | B20: 45817 | C20: =_xlfn.DAYS(TODAY(),B20) -> 268 | D20: 170522 | E20: 08_Service | F20: Warehouse | G20: Tires Storeman | H20: 30.000 + 0 - 10.000 VB | I20: Luboš Štangler | J20: Honza | K20: AAA, jobdnes, dobrá práce, práce cz,inwork | L20: New request | M20: 0 | N20: 3 | O20: 2 | P20: 1
A21: RPL (fill cap) | B21: 45800 | C21: =_xlfn.DAYS(TODAY(),B21) -> 285 | D21: 169630 | E21: 08_Service | F21: Service | G21: Smart Repair Technician - AVIA | H21: 26 000+ 0-14 000 VB | I21: Petr Šimeček/Miloš Ponáhlý | J21: Mirka | K21: AAA, jobdnes, volnamista, dobrá práce, práce cz,inwork | L21: Hiring: Vejvoda (LP) | M21: 0 | N21: 1 | O21: 0 | P21: 1
A22: RPL (fill cap) | B22: 45586 | C22: =_xlfn.DAYS(TODAY(),B22) -> 499 | D22: 154898 | E22: 08_Service | F22: Service | G22: Panel Beater | H22: negotiable | I22: Miroslav Knap | J22: Honza | K22: AAA, práce.cz, pracezarohem, dobraprace | L22: Checking CVs | M22: 0 | N22: 2 | O22: 0 | P22: 1
A23: NEW CAP | B23: 45755 | C23: =_xlfn.DAYS(TODAY(),B23) -> 330 | D23: 167206 | E23: 07_Stock & Logistics | F23: Stock | G23: Stock Controller - Znojmo | H23: 25 000 + 0- 25 000 VB | I23: Borovec Josef | J23: Blanka | K23: AAA, práce.cz, pracezarohem, dobraprace | L23: Hiring Tihlařík (1.7.) Checking CV | M23: 6 | N23: 1 | O23: 0 | P23: 1
A24: RPL Hánová | B24: 45783 | C24: =_xlfn.DAYS(TODAY(),B24) -> 302 | D24: 168833 | E24: 07_Stock & Logistics | F24: Stock | G24: Courier DPP - Otrokovice | H24: 125,-Kč/hod. | I24: Borovec Josef/Michal Hroch | J24: Mirka | K24: AAA, práce.cz, pracezarohem, dobraprace | L24: Checking CVs | M24: 1 | N24: 1 | O24: 0 | P24: 1
A25: RPL (Macháčková) | B25: 45797 | C25: =_xlfn.DAYS(TODAY(),B25) -> 288 | D25: waiting for | E25: 07_Stock & Logistics | F25: Stock | G25: Courier DPP - České Budějovice | H25: 125,-Kč/hod. | I25: Borovec Josef | J25: Mirka | K25: AAA, práce cz., pracezarohem, dobraprace, jobdnes | L25: For 1st: Maxová, Tuma (5.6) | M25: 6 | N25: 1 | O25: 1 | P25: 1
A26: RPL (Soukup) | B26: 45796 | C26: =_xlfn.DAYS(TODAY(),B26) -> 289 | D26: 169251 | E26: 02_Car Sales | F26: Customer Care | G26: Customer Care Technician - Praha | H26: 35 000 + 0-11 000 KPI | I26: Žerebný Michal | J26: Blanka | K26: AAA, práce.cz, pracezarohem, dobraprace, volnamista, jobdnes | L26: For 2nd Pudil, Reil (13.6.) Checking CV | M26: 4 | N26: 3 | O26: 2 | P26: 1
A27: RPL (Müller, Šimek, Sedláček) | B27: 45782 | C27: =_xlfn.DAYS(TODAY(),B27) -> 303 | D27: 168761 154646 | E27: 05_Car Purchase | F27: Pricing | G27: Pricing Expert | H27: 30 000 + 0 - 10 000 VB (GB 3m) | I27: Jiří Somol | J27: Anna K. | K27: AAA, práce.cz, jobs.cz, dobraprace, volnamista, jobdnes | L27: Hiring: Vitouš (1.8.) Last h: Tejnický (2. 6.),, Griessl (5.5.), Osagiede (1. 4.), Rudiš (3.3.) | M27: 19 | N27: 36 | O27: 34 | P27: 1
A28: RPL (fill cap) | B28: 45761 | C28: =_xlfn.DAYS(TODAY(),B28) -> 324 | D28: 170023 170515 | E28: 05_Car Purchase | F28: Mobile Buying | G28: Mobile Buyer - Praha | H28: 25000+VB | I28: Tomáš Kaprálek | J28: Mirka | K28: AAA, práce.cz, pracezarohem, dobraprace | L28: For 1st: Beránek (4.6), Srna (11.6) Hiring: Koc (14.4) Not suitable: Hořínek | M28: 30 | N28: 8 | O28: 7 | P28: 2
A29: RPL (fill cap) | B29: 45775 | C29: =_xlfn.DAYS(TODAY(),B29) -> 310 | D29: 170015 | E29: 05_Car Purchase | F29: Mobile Buying | G29: Mobile Buyer - Otrokovice | H29: 25000+VB | I29: Tomáš Kaprálek | J29: Mirka | K29: AAA, práce.cz, pracezarohem, dobraprace | L29: nev request | M29: 0 | N29: 1 | O29: 1 | P29: 1
B30: MOTOTECHNA | L30: ) | N30: =SUM(N31:N33) -> 4 | O30: =SUM(O31:O33) -> 4 | P30: =SUM(P31:P33) -> 3
A31: RPL (Todorov) | B31: 45775 | C31: =_xlfn.DAYS(TODAY(),B31) -> 310 | D31: Waiting for RFP | E31: 16_Mototechna | F31: Mototechna Drive | G31: Operations Manager | H31: Negotiable | I31: Jan Hrubý | J31: Anna K. | K31: AAApráce, jobs | L31: For 2nd: Čori, Jonáš No: Mayrichová, Sattler, Zuber | M31: 7 | N31: 1 | O31: 1 | P31: 1
A32: RPL (Flek) | B32: 45790 | C32: =_xlfn.DAYS(TODAY(),B32) -> 295 | D32: 170028 | E32: 16_Mototechna | F32: Mototechna 2.0 | G32: Car Trader | H32: negotiable | I32: Jan Hrubý | J32: Anna K. | K32: AAApráce, jobs | L32: NO: Ben Nasim, Novák, Palokaj | N32: 3 | O32: 2 | P32: 1
A33: NEW | B33: 45782 | C33: =_xlfn.DAYS(TODAY(),B33) -> 303 | D33: DPP | E33: 16_Mototechna | F33: Mototechna 2.0 | G33: Driver_Mototechna 2.0 | H33: 150 Kč/hod | I33: Michal Kučera | J33: Anna K. | K33: AAA | L33: Hiring: Foldin (dle LP červen), Omluvil se z pohovoru: Sůva (19.5.) | M33: 5 | N33: 0 | O33: 1 | P33: 1
A34: Reg. Praha | B34: PRAGUE BRANCH | N34: =SUM(N35:N42) -> 138 | O34: =SUM(O35:O42) -> 130 | P34: =SUM(P35:P42) -> 16
A35: RPL (fill cap) | B35: 45792 | C35: =_xlfn.DAYS(TODAY(),B35) -> 293 | D35: 170558 170556 170555 | E35: 02_Car Sales | F35: Selling | G35: Salesman - Praha | H35: 22 000 / 25 000 + % NP 30 | I35: Petr Neckař | J35: Ondra | K35: AAA, práce.cz, jobs.cz, dobraprace, volnamista, jobdnes, FB | L35: Hired 1.7. Grayton, Olashy, Bílý, Kotouček, Dunda (1.8.) | M35: 58 | N35: 38.5 | O35: 37.5 | P35: 3
A36: RPL (Rybínová, Hudeková) | B36: 45758 | C36: =_xlfn.DAYS(TODAY(),B36) -> 327 | D36: 167171 168467 | E36: 02_Car Sales | F36: Selling | G36: Receptionist | H36: 22.000 + 0 - 10.000 | I36: Petr Neckař | J36: Ondra | K36: AAA, práce | L36: Hired 1.6. Kralertová (1/2), 1.7. Chlupáčová (1/2) | N36: 4.5 | O36: 5 | P36: 1
A37: RPL(Fill cap, Ravič) | B37: 45810 | C37: =_xlfn.DAYS(TODAY(),B37) -> 275 | D37: 165511 170511 | E37: 03_Financial Services | F37: Selling Support | G37: Customer Service Specialist - Praha | H37: 25.000 + % | I37: David Hlavnička/Tereza Holečková | J37: Mirka | K37: AAA, párce.cz, párce za rohem, jobs.cz | L37: Hired: Gallik (2.6) IM: Adamová Valerie No after PD: Kvasničková No after 1st.: Fialka, Rothanzl, Formanová (not suitable) Refused offer: Hrabarova, Valentová, Brabec | M37: 35 | N37: 28 | O37: 27.5 | P37: 2
A38: RPL (fill cap) | B38: 45742 | C38: =_xlfn.DAYS(TODAY(),B38) -> 343 | D38: 162756 167792 167799 | E38: 05_Car Purchase | F38: Buying | G38: Test Driver | H38: 22 000 + % | I38: Petr Kuchynka | J38: Blanka | K38: AAA, párce.cz, párce za rohem, | L38: Hiring Žilka (1.8.) For 2nd Bakalář (9.6.) No after 2nd Slabý, Vinklář, Tkadlec, Horvát, Bittner, Dupal Didnt come Kubánek, Rolenc, Moravec, Beneš Checking CV | M38: 16 | N38: 20 | O38: 16 | P38: 3
A39: RPL (fill cap) | B39: 45810 | C39: =_xlfn.DAYS(TODAY(),B39) -> 275 | D39: HPP | E39: 02_Car Sales | F39: Selling | G39: Assistant Salesman | H39: 25.000 + 15.000 | I39: Petr Neckař | J39: Ondra | K39: AAA, práce, jobs | L39: After 2nd Kovalenko Hired 2.6. Stehlík No after 2nd 2x | M39: 9 | N39: 12 | O39: 10 | P39: 2
A40: RPL (Kroc) | B40: 45799 | C40: =_xlfn.DAYS(TODAY(),B40) -> 286 | D40: 169572 | E40: 04_Automotive OPS | F40: OPS (Full Time) | G40: Helper_Boxy | H40: 26 000 + 0 - 8000 | I40: Jan Malchar | J40: Anna K. | K40: AAA | L40: Hiring: Gomba Jan (dle lp červen) | M40: 1 | N40: 6 | O40: 6 | P40: 1
A41: RPL (Ljubimcev, Hlaváč)) | B41: 45777 | C41: =_xlfn.DAYS(TODAY(),B41) -> 308 | D41: 168454, 168452 | E41: 04_Automotive OPS | F41: OPS (Full Time) | G41: Fotograf _Praha | H41: 26 000 + 0 - 8000 | I41: František Kudrna | J41: Anna K. | K41: AAA, párce.cz, párce za rohem, jobs.cz | L41: IM: Kmochová (1.6.), Hiring: Scaletta (11.6.) | M41: 3 | N41: 2 | O41: 2 | P41: 2
A42: RPL (Silný Lukáš+Fill CAP) | B42: 45790 | C42: =_xlfn.DAYS(TODAY(),B42) -> 295 | D42: Waiting for RFP 2x | E42: 04_Automotive OPS | F42: OPS (Full Time) | G42: Helper _Praha | H42: 26 000 + 0 - 8000 | I42: Jan Malchar | J42: Anna K. | K42: AAA, párce.cz, práce za rohem | L42: Hiring: Fábik (červen?) | M42: 1 | N42: 27 | O42: 26 | P42: 2
A43: Reg. Praha | B43: ČESTLICE | N43: =SUM(N44:N47) -> 23 | O43: =SUM(O44:O47) -> 20 | P43: =SUM(P44:P47) -> 4
A44: RPL (Šoltys) | B44: 45800 | C44: =_xlfn.DAYS(TODAY(),B44) -> 285 | D44: 169530 | E44: 02_Car Sales | F44: Selling | G44: Salesman - Čestlice | H44: 25.000 + 0 - 25.000 | I44: Petr Neckař | J44: Ondra | K44: AAA, práce.cz, inwork, dobraprace, jobdnes | L44: For 2nd 1x | M44: 2 | N44: 5 | O44: 5 | P44: 1
A45: RPL(Panzenbergerová) | B45: 45813 | C45: =_xlfn.DAYS(TODAY(),B45) -> 272 | D45: 170509 | E45: 03_Financial Services | F45: Selling Support | G45: Customer Service Specialist - Čestlice | H45: 25.000 + % | I45: David Hlavnička/Tereza Holečková | J45: Mirka | K45: AAA, párce.cz, párce za rohem, jobs.cz | L45: New request | M45: 0 | N45: 5 | O45: 4 | P45: 1
A46: RPL (Zacharkyv) | B46: 45777 | C46: =_xlfn.DAYS(TODAY(),B46) -> 308 | D46: 168450 | E46: 04_Automotive OPS | F46: OPS (Full Time) | G46: Helper - Čestlice | H46: 26 000 + 0 - 8000 | I46: Jan Malchar | J46: Anna K. | K46: AAA, práce.cz, inwork, dobraprace, jobdnes | L46: Didnt come to the int: Novák (4. 6. 2025) No after 2nd: Lacinová | M46: 4 | N46: 8 | O46: 7 | P46: 1
A47: RPL (Řehoř) | B47: 45770 | C47: =_xlfn.DAYS(TODAY(),B47) -> 315 | D47: 166297 | E47: 05_Car Purchase | F47: Buying | G47: Test Driver - Čestlice | H47: (50 000GM) FB | I47: Lukáš Geršic | J47: Kamila | K47: AAA, práce.cz, inwork, dobraprace, jobdnes | L47: Checking CVs Hired: Hořínek (23.4.) Refused offer: Jelínek, Wetzstein No after 2nd: Lán, Kucharczyk Didn´t come: Zeman | M47: 15 | N47: 5 | O47: 4 | P47: 1
A48: Reg. Praha | B48: KLECANY | N48: 0 | O48: 0 | P48: =SUM(P49) -> 1
A49: RPL (Fill cap) | B49: 45790 | C49: =_xlfn.DAYS(TODAY(),B49) -> 295 | D49: 169571 | E49: 04_Automotive OPS | F49: OPS (Full Time) | G49: Helper _Klecany | H49: 26 000 + 0 - 8000 | I49: Jan Malchar | J49: Anna K. | K49: AAA, párce.cz, práce za rohem | L49: Hiring: Jindřich Lukáš (dle LP červen) IM: Doležal | N49: 2 | O49: 1 | P49: 1
A50: BRANCHES | N50: =N51+N56+N58+N60+N66+N71+N72+N76+N81+N86+N88+N92+N97+N101+N103+N104+N105+N107+N110+N113 -> #REF! | O50: =O51+O56+O58+O60+O66+O71+O72+O76+O81+O86+O88+O92+O97+O101+O103+O104+O105+O107+O110+O113 -> #REF! | P50: =P51+P56+P58+P60+P66+P71+P72+P76+P81+P86+P88+P92+P97+P101+P103+P104+P105+P107+P110+P113 -> 58
A51: Bohemia 1 | B51: ČESKÉ BUDĚJOVICE | N51: =SUM(N52:N55) -> 11.25 | O51: =SUM(O52:O55) -> 10 | P51: =SUM(P52:P55) -> 4
A52: RPL (fill cap) | B52: 45797 | C52: =_xlfn.DAYS(TODAY(),B52) -> 288 | D52: 166984 | E52: 02_Car Sales | F52: Selling | G52: Site Manager - České Budějovice | H52: 40 000 + % | I52: Varmuža Miroslav | J52: Blanka | K52: AAA, práce.cz,dobraprace, volnamista, jobdnes | L52: For 1st Nutz Checking CV | M52: 15 | N52: 3 | O52: 2 | P52: 1
A53: RPL (Bohoňková) | B53: 45782 | C53: =_xlfn.DAYS(TODAY(),B53) -> 303 | D53: 165509 | E53: 03_Financial Services | F53: Selling Support | G53: Customer Service Specialist - České Budějovice | H53: 22 000 + % NP 30 | I53: Vaska Tomáš | J53: Blanka | K53: AAA, práce.cz, jobs.cz, dobraprace, volnamista, jobdnes | L53: Hired Pešková (2.6.) Get offer Rajnochová Hired Tolingerová (5.5.) No after 2nd Klásková, Holzelová, Nováková, Chvojka, Smržová, Svatoň, Vandová, Procházka, Bureš, Dolejšová, Šafářová, Studený Didnt come Melchrová, Turek, Novotná, Koubalík Checking CV | M53: 59 | N53: 6 | O53: 6 | P53: 1
A54: RPL (Jaroš) | B54: 45811 | C54: =_xlfn.DAYS(TODAY(),B54) -> 274 | D54: 170693 | E54: 05_Car Purchase | F54: Buying | G54: Test driver - České Budějovice | H54: 22 000 + % | I54: Marcel Ronge | J54: Anička | K54: AAA, práce.cz, inwork, dobraprace, jobdnes | L54: New request | M54: 0 | N54: 2 | O54: 2 | P54: 1
A55: RPL (Šafářová) | B55: 45797 | C55: =_xlfn.DAYS(TODAY(),B55) -> 288 | D55: 1xDPP | E55: 04_Automotive OPS | F55: OPS (Part time) | G55: Office cleaner - Budějce | H55: 125,- Kč/hod | I55: Jan Sokola | J55: Anička | K55: AAA, dobraprace, fajnbrigady, jobdnes | L55: Checking CV's Medicaly unsuitable Dušková Didn't come Boubelíková, Pospíšilová | M55: 15 | N55: 0.25 | O55: 0.25 | P55: 1
A56: Bohemia 1 | B56: CHOMUTOV | N56: =SUM(N57) -> 6 | O56: =SUM(O57) -> 5 | P56: =SUM(P57) -> 1
A57: RPL (Brotánek) | B57: 45804 | C57: =_xlfn.DAYS(TODAY(),B57) -> 281 | D57: 169864 | E57: 04_Automotive OPS | F57: OPS | G57: Helper - Chomutov | H57: 26 000 + 0 - 4 000 VB | I57: Martin Čížek | J57: Blanka | K57: AAA, dobraprace, práce.cz, pracezarohem | L57: Hiring Jelenok Checking CV | M57: 1 | N57: 6 | O57: 5 | P57: 1
A58: Bohemia 1 | B58: KLADNO | N58: =SUM(N59:N59) -> 2 | O58: =SUM(O59:O59) -> 1 | P58: =SUM(P59:P59) -> 1
A59: RPL (fill cap) | B59: 45733 | C59: =_xlfn.DAYS(TODAY(),B59) -> 352 | D59: DPP | E59: 02_Car Sales | F59: Selling | G59: Assistant Salesman_part time - Kladno | H59: 150 Kč / hod | I59: Varmuža Miroslav | J59: Blanka | K59: AAA, fajnbrigady | L59: Checking CV | M59: 11 | N59: 2 | O59: 1 | P59: 1
A60: Bohemia 1 | B60: PLZEŇ | N60: =SUM(N61:N64) -> 22 | O60: =SUM(O61:O64) -> 17 | P60: =SUM(P61:P65) -> 9
A61: RPL (Šalom) | B61: 45796 | C61: =_xlfn.DAYS(TODAY(),B61) -> 289 | D61: 169005 | E61: 02_Car Sales | F61: Selling | G61: Salesman - Plzeň | H61: 22 000 + % | I61: Miroslav Varmuža | J61: Blanka | K61: AAA, jobs, práce, pracezarohem | L61: No after 2nd Hora, Dvořák, Strejc Checking CVs | M61: 21 | N61: 8 | O61: 7 | P61: 1
A62: RPL (Cingrošová, Rudnytska, Jelínková) | B62: 45782 | C62: =_xlfn.DAYS(TODAY(),B62) -> 303 | D62: 166752 138912 | E62: 03_Financial Services | F62: Selling Support | G62: Customer Service Specialist - Plzeň | H62: 22 000 + % NP | I62: Vaska Tomáš | J62: Blanka | K62: AAA, práce.cz, inwork, dobraprace, jobdnes | L62: For 2nd Tomášková, Háčiková (6.6.) Hired Malásková, Jelínková (5.5.) Refused offer Kadečková, Sinkulová, Hesounová, Hoštová Hiring Lerch (1.4.) FR No after 2nd Jindřichová, Braunová, Šatrová, Rundtov, Beňo, Nusková, Faitová, Krejčová | M62: 21 | N62: 8 | O62: 5 | P62: 3
A63: RPL (fill cap) | B63: 45670 | C63: =_xlfn.DAYS(TODAY(),B63) -> 415 | D63: 162238 | E63: 05_Car Purchase | F63: Buying | G63: Test driver - Plzeň | H63: (50 000 GM) | I63: Lukáš Geršic | J63: Kamila | K63: AAA, práce.cz, práce.cz, inwork, dobraprace, jobdnes | L63: Waiting for decision: Dolejš (21.5.) Didn´t come: Fleisner No after phsc: Červenka | M63: 87 | N63: 6 | O63: 5 | P63: 1
A64: NEW | B64: 45691 | C64: =_xlfn.DAYS(TODAY(),B64) -> 394 | D64: 162968 162964 | E64: 05_Car Purchase | F64: Buying | G64: Test driver - Příbram | H64: 22 000 + 0 - 18 000 | I64: Lukáš Geršic | J64: Kamila | K64: AAA, práce.cz, práce za rohem, dobrá práce, jobdnes | L64: No after 2nd: Lán 1x bude obsazeno IM - Hořínek ze Sokolova (už máme náhradu) | M64: 15 | N64: 0 | O64: 0 | P64: 2
A65: RPL (Kabeš, Zrůst) | B65: 45799 | C65: =_xlfn.DAYS(TODAY(),B65) -> 286 | D65: 169516 169515 | E65: 04_Automotive OPS | F65: OPS (Full Time) | G65: Helper - Plzeň | H65: 26 000 + 0 - 8 000 VB | I65: Čížek Martin | J65: Blanka | K65: AAA, práce.cz, práce za rohem, dobrá práce, jobdnes | L65: For 2nd Ackermann (12.6.) Checking CV's | M65: 14 | N65: 11 | O65: 11 | P65: 2
A66: Bohemia 1 | B66: SOKOLOV | N66: =SUM(N67:N69) -> 19 | O66: =SUM(O67:O69) -> 16 | P66: =SUM(P67:P69) -> 5
A67: RPL (Fill cap) | B67: 45693 | C67: =_xlfn.DAYS(TODAY(),B67) -> 392 | D67: 163604 | E67: 03_Financial Services | F67: Selling Support | G67: Customer Service Specialist - Sokolov | H67: 22 000 + % NP | I67: Vaska Tomáš | J67: Blanka | K67: AAA, práce.cz, jobs.cz, dobraprace, volnamista, jobdnes | L67: Didnt start Korbelová (1.6.) No after 2nd Gareisová, Čerňanská, Beňo Checking CV | M67: 21 | N67: 5 | O67: 4 | P67: 1
A68: RPL (Bulíček) + IM Kamír | B68: 45804 | C68: =_xlfn.DAYS(TODAY(),B68) -> 281 | D68: 169818 | E68: 02_Car Sales | F68: Selling | G68: Salesman - Sokolov | H68: 22 000 + % | I68: Varmuža Miroslav | J68: Blanka | K68: AAA, dobraprace, inwork, pracezarohem, práce cz | L68: For 2nd Štika (9.6.) Checking CV | M68: 18 | N68: 5 | O68: 6 | P68: 1
A69: RPL (Fill cap) | B69: 45765 | C69: =_xlfn.DAYS(TODAY(),B69) -> 320 | D69: 162942 166404 166774 | E69: 04_Automotive OPS | F69: OPS (Full time) | G69: Helper - Sokolov | H69: 26 000 + 0 - 4 000 | I69: Čížek Martin | J69: Blanka | K69: AAA, dobraprace, inwork, pracezarohem, práce cz | L69: Hiring Sawruk, Šeděnka Hired Šašek, Stejskal, Hanková, Štiák Didnt start Schottner (10.3.) No after 2nd Mencl, Melničuk, Šarišský, Skoumal, Forro Checking CV | M69: 26 | N69: 9 | O69: 6 | P69: 3
A70: RPL (Fill cap) | B70: 45810 | C70: =_xlfn.DAYS(TODAY(),B70) -> 275 | D70: DPP | E70: 04_Automotive OPS | F70: OPS (Part time) | G70: Driver Part time - Sokolov | H70: 125,-Kč/hod. | I70: Čížek Martin | J70: Mirka | K70: AAA, dobraprace, inwork, pracezarohem, práce cz | L70: Hiring: Tirindová (LP) | M70: 5 | N70: 0 | O70: 0 | P70: 1
A71: Bohemia 1 | B71: TÁBOR | N71: =SUM(#REF!) -> #REF! | O71: =SUM(#REF!) -> #REF! | P71: 0
A72: Bohemia 2 | B72: HRADEC KRÁLOVÉ | N72: =SUM(N73:N75) -> 8 | O72: =SUM(O73:O75) -> 6 | P72: =SUM(P73:P75) -> 3
A73: RPL (Válek + Vejnar) | B73: 45810 | C73: =_xlfn.DAYS(TODAY(),B73) -> 275 | D73: 169547 | E73: 02_Car Sales | F73: Selling | G73: Salesman - Hradec Králové | H73: 22.000 + % (50 GB) | I73: Petr Kalabis | J73: Anička | K73: AAA, dobraprace, inwork, pracezarohem, práce cz | L73: Checking CV's Hired Dušek (2.6) No fater 2nd Fajt, Hanuš, Růžička | M73: 10 | N73: 6 | O73: 6 | P73: 1
A74: RPL (Fill cap) | B74: 45748 | C74: =_xlfn.DAYS(TODAY(),B74) -> 337 | D74: 162413 165531 | E74: 04_Automotive OPS | F74: OPS (Part time) | G74: Helper - Hradec Králové | H74: 125,-Kč/h | I74: Roman Nekola | J74: Mirka | K74: AAA, dobraprace, inwork, pracezarohem, práce cz | L74: Hiring: Hlavatý (LP) | M74: 2 | N74: 2 | O74: 0 | P74: 1
A75: RPL (Fill cap) | B75: 45803 | C75: =_xlfn.DAYS(TODAY(),B75) -> 282 | D75: DPP | E75: 04_Automotive OPS | F75: OPS (Part time) | G75: Driver - Hradec Králové | H75: 125,-Kč/h | I75: Roman Nekola | J75: Mirka | K75: AAA, dobraprace, inwork, pracezarohem, práce cz | L75: Hiring: Marek(2.6/LP) | M75: 1 | N75: 0 | O75: 0 | P75: 1
A76: Bohemia 2 | B76: KOLÍN | N76: =SUM(N77:N78) -> 4.5 | O76: =SUM(O77:O78) -> 3.5 | P76: =SUM(P77:P80) -> 4
A77: RPL (Kroužecká) | B77: 45691 | C77: =_xlfn.DAYS(TODAY(),B77) -> 394 | D77: 161947 | E77: 03_Financial Services | F77: Selling Support | G77: Customer Service Specialist - Kolín | H77: 25.000 + % NP 30 000 | I77: Martin Kotlán | J77: Kamila | K77: AAA, práce.cz, práce za rohem, jobs.cz | L77: Refused offer: Slavíčková, Talacko Didn´t come: Svobodová, Kumbera, Zadražil No after 2nd: Pichl, Kočerhán Hired: Volencová 3.2. | M77: 33 | N77: 4 | O77: 3 | P77: 1
A78: RPL (Blechová) | B78: 45691 | C78: =_xlfn.DAYS(TODAY(),B78) -> 394 | D78: 163834 | E78: 04_Automotive OPS | F78: OPS (Part time) | G78: Office Cleaner - Kolín | H78: 125 Kč/hod | I78: Roman Nekola | J78: Mirka | K78: AAA, práce.cz, práce za rohem, jobs.cz | L78: Hiring: Apltauerová (1.7) Refused offer: Ptáčková, Pixalová (24.2) | M78: 15 | N78: 0.5 | O78: 0.5 | P78: 1
A79: RPL (fill cap) | B79: 45813 | C79: =_xlfn.DAYS(TODAY(),B79) -> 272 | D79: DPP | E79: 04_Automotive OPS | F79: OPS (Part time) | G79: Driver DPP- Kolín | H79: 125 Kč/hod | I79: Roman Nekola | J79: Mirka | K79: AAA, práce.cz, práce za rohem, jobs.cz | L79: New request | M79: 0 | N79: 0 | O79: 0 | P79: 1
A80: RPL (fill cap) | B80: 45789 | C80: =_xlfn.DAYS(TODAY(),B80) -> 296 | D80: DPP | E80: 04_Automotive OPS | F80: OPS (Part time) | G80: Helper DPP- Kolín | H80: 125 Kč/hod | I80: Roman Nekola | J80: Mirka | K80: AAA, práce.cz, práce za rohem, jobs.cz | L80: Checking CVs | M80: 2 | N80: 0.5 | O80: 0 | P80: 1
A81: Bohemia 2 | B81: LIBEREC | N81: =SUM(N82:N83) -> 15 | O81: =SUM(O82:O83) -> 16 | P81: =SUM(P82:P85) -> 6
A82: RPL (Luprich) | B82: 45792 | C82: =_xlfn.DAYS(TODAY(),B82) -> 293 | D82: 169546 | E82: 02_Car Sales | F82: Selling | G82: Salesman - Liberec | H82: 22 000 + % | I82: Petr Kalabis | J82: Anička | K82: AAA, fajn brigády, Job dnes | L82: Hiring Kryvljak (1.7) | M82: 20 | N82: 8 | O82: 9 | P82: 1
A83: RPL (Kučírek,Čečatka) | B83: 45770 | C83: =_xlfn.DAYS(TODAY(),B83) -> 315 | D83: 169997 | E83: 04_Automotive OPS | F83: OPS (Full time) | G83: Helper - Liberec | H83: 26 000 + 0 - 4 000 | I83: Roman Nekola | J83: Mirka | K83: AAA, dobraprace, inwork, pracezarohem, práce cz | L83: Hiring:Vlach (LP) Filiip (LP) Hired: Goda, (24.3), Vítek (23.4) For 1st: Marek(4.6) Offer: Mikula(refused offer) No after 1st: Říha, Šoltys, Kuča, Koťátko, Hausler (not suitable) Karala, Pech (didnt comme) Dindt start: Pollach | M83: 84 | N83: 7 | O83: 7 | P83: 2
A84: RPL (Fill cap) | B84: 45789 | C84: =_xlfn.DAYS(TODAY(),B84) -> 296 | D84: DPP | E84: 04_Automotive OPS | F84: OPS (Part time) | G84: Helper - Liberec | H84: 26 000 + 0 - 4 000 | I84: Roman Nekola | J84: Mirka | K84: AAA, dobraprace, inwork, pracezarohem, práce cz | L84: new request | M84: 0 | N84: 0 | O84: 0 | P84: 2
A85: RPL (Fill cap) | B85: 45709 | C85: =_xlfn.DAYS(TODAY(),B85) -> 376 | D85: DPP | E85: 04_Automotive OPS | F85: OPS (Part time) | G85: Driver - Liberec | H85: 125 Kč/hod | I85: Roman Nekola | J85: Mirka | K85: AAA, dobraprace, inwork, pracezarohem, práce cz | L85: For 1st: Androš(2.5), Mandík (16.5) Didnt comme: Roubalová, Rondoš, Urban (28.4).Cicko (4.4) | M85: 47 | N85: 0 | O85: 0.5 | P85: 1
A86: Bohemia 2 | B86: MLADÁ BOLESLAV | M86: , | N86: =SUM(#REF!) -> #REF! | O86: =SUM(#REF!) -> #REF! | P86: =SUM(P87) -> 1
A87: RPL (Fill cap) | B87: 45797 | C87: =_xlfn.DAYS(TODAY(),B87) -> 288 | D87: DPP | E87: 04_Automotive OPS | F87: OPS (Part time) | G87: Driver - Mladá Boleslav | H87: 125 Kč/hod | I87: Roman Nekola | J87: Mirka | K87: AAA, dobraprace, inwork, pracezarohem, práce cz | L87: Hired: Houžvic (20.5) No after 1st: Šmída (not suitable) | M87: 18 | N87: 0 | O87: 0.5 | P87: 1
A88: Bohemia 2 | B88: TEPLICE | N88: =SUM(#REF!) -> #REF! | O88: =SUM(#REF!) -> #REF! | P88: =SUM(P89:P91) -> 3
A89: RPL (Maršíčková - LTS) | B89: 45791 | C89: =_xlfn.DAYS(TODAY(),B89) -> 294 | D89: 169088 | E89: 03_Financial Services | F89: Selling Support | G89: Customer Service Specialist - Teplice | H89: 25.000 + % | I89: Martin Kotlán | J89: Kamila | K89: AAA, práce.cz, práce za rohem, jobs.cz | L89: Refused offer: Janda | M89: 15 | N89: 4 | O89: 4 | P89: 1
A90: RPL (Vála) | B90: 45784 | C90: =_xlfn.DAYS(TODAY(),B90) -> 301 | D90: 168093 | E90: 04_Automotive OPS | F90: OPS (Full Time) | G90: Helper - Teplice | H90: 26 000 + 0 - 4 000 VB | I90: Čížek Martin | J90: Blanka | K90: AAA, práce.cz, práce za rohem, dobraprace | L90: Hiring Janoušek No after 2nd Jelenok, Do Hoai, Jordán, Procházka Checking CV | M90: 16 | N90: 4 | O90: 3 | P90: 1
A91: RPL (Fill cap) | B91: 45804 | C91: =_xlfn.DAYS(TODAY(),B91) -> 281 | D91: DPP | E91: 04_Automotive OPS | F91: OPS (Part time) | G91: Driver - Teplice | H91: 125 Kč/hod | I91: Martin Čížek | J91: Mirka | K91: AAA, dobraprace, inwork, pracezarohem, práce cz | L91: Hired: Chrž, Brych (27.5) | M91: 0 | N91: 1 | O91: 0.5 | P91: 1
A92: Bohemia 2 | B92: ÚSTÍ NAD LABEM | N92: =SUM(N93:N96) -> 18 | O92: =SUM(O82:O85) -> 16.5 | P92: =SUM(P93:P96) -> 5
A93: RPL (Piotrovský) | B93: 45810 | C93: =_xlfn.DAYS(TODAY(),B93) -> 275 | D93: 170133 | E93: 02_Car Sales | F93: Selling | G93: Salesman - Ústí nad Labem | H93: 22 000 + % | I93: Petr Kalabis | J93: Anička | K93: AAA, práce.cz, práce za rohem, inwork, dobraprace | L93: New request | M93: 0 | N93: 5 | O93: 4 | P93: 1
A94: RPL (Henychová, Betyárová) | B94: 45791 | C94: =_xlfn.DAYS(TODAY(),B94) -> 294 | D94: 169088 | E94: 03_Financial Services | F94: Selling Support | G94: Customer Service Specialist -Ústí nad Labem | H94: 25.000 + % | I94: Martin Kotlán | J94: Kamila | K94: AAA, práce.cz, práce za rohem, jobs.cz | L94: Checking CVs | M94: 20 | N94: 5 | O94: 5 | P94: 1
A95: RPL (fill cap) | B95: 45784 | C95: =_xlfn.DAYS(TODAY(),B95) -> 301 | D95: 168092 165106 | E95: 04_Automotive OPS | F95: OPS (Full Time) | G95: Helper - Ústí nad Labem | H95: 26 000 + 0 - 4 000 VB | I95: Čížek Martin | J95: Blanka | K95: AAA, práce.cz, práce za rohem, dobraprace | L95: Hiring Číhal No after 2nd Kakeš, Plachý Checking CV | M95: 23 | N95: 8 | O95: 6 | P95: 2
A96: RPL (fill CAP) | B96: 45792 | C96: =_xlfn.DAYS(TODAY(),B96) -> 293 | D96: 168091 | E96: 04_Automotive OPS | F96: OPS (Part time) | G96: Driver - Ústí nad Labem | H96: 125,-Kč/h | I96: Martin Čížek | J96: Mirka | K96: AAA, dobraprace, inwork, pracezarohem, práce cz | L96: Hired: Kurucz (15.5) Hiring: Verba (LP) IM:Jungmann | M96: 50 | N96: 0 | O96: 0 | P96: 1
A97: Moravia 1 | B97: BRNO | N97: =SUM(#REF!) -> #REF! | O97: =SUM(#REF!) -> #REF! | P97: =SUM(P98:P100) -> 5
A98: RPL (Stehlíček, Kotyza, Hrňa) | B98: 45817 | C98: =_xlfn.DAYS(TODAY(),B98) -> 268 | D98: 170623 170624 170625 | E98: 02_Car Sales | F98: Selling | G98: Salesman - Brno | H98: 22.000 + % | I98: Tomáš Krmela | J98: Ondra | K98: AAA, párce.cz, párce za rohem, jobs.cz | L98: For 2nd 6x Got offer Štefan Hired 2.6. Souček Stopped communicating Grolinski Refused offer Míča (fix) | M98: 46 | N98: 16 | O98: 16 | P98: 2
A99: RPL (Butorová) | B99: 45810 | C99: =_xlfn.DAYS(TODAY(),B99) -> 275 | D99: 166884 | E99: 03_Financial Services | F99: Selling Support | G99: Customer Service Specialist - Brno | H99: 22.000 + % | I99: Martin Havel | J99: Mirka | K99: AAA, párce.cz, párce za rohem, jobs.cz | L99: Hiring: Bačáková (2.6)Dostálová,Procházka (1.7) For 1st: Svobodová. (22.5), Pitour, Dostálová(23.5), Bačáková, Šlapanský (27.5) No after 1st: Dvořák, Tokarev, Stojanová, Stloukal,Lar (not suitable) | M99: 4 | N99: 14 | O99: 12 | P99: 1
A100: RPL (Fill cap) | B100: 45744 | C100: =_xlfn.DAYS(TODAY(),B100) -> 341 | D100: 167858 | E100: 05_Car Purchase | F100: Buying | G100: Test Driver - Brno | H100: 22 000 + 0 - 18 000 GB ve ZD | I100: Martin Kostelka | J100: Anna K. | K100: AAA, párce.cz, párce za rohem, jobs.cz | L100: Nenastoupil: Bednář (2. 6. 2025) No after 2nd: Cink | M100: 21 | N100: 5 | O100: 3 | P100: 2
...

Sheet VAC_History
A1: Date | B1: Total VAC
A2: 45625 | B2: 70.75
A3: 45642 | B3: 66.25
A4: 45646 | B4: 67.25
A5: 45656 | B5: 67.25
A6: 45666 | B6: 59.25
A7: 45674 | B7: 76.5
A8: 45681 | B8: 78.5
A9: 45695 | B9: 112
A10: 45702 | B10: 119
A11: 45709 | B11: 121.25
A12: 45711 | B12: 121.25
A13: 45716 | B13: 128.75
... A58: 46084 | B58: 103

Sheet Podrobnosti1
A1: Podrobnosti pro Vacancies – Division: 05_Car Purchase
A3: Status | B3: Place | C3: Date of opening | D3: Time to fill | E3: Request for position | F3: Division | G3: Department | H3: Position | I3: Salary | J3: Hiring Manager | K3: Generalist | L3: Sources | M3: Comments | N3: CAP | O3: ACTUAL | P3: VAC
A4: NEW | B4: Jihlava (Třebíč) | C4: 45947 | D4: 28 | E4: 179003 | F4: 05_Car Purchase | G4: Buying | H4: Test driver - Jihlava (Třebíč) | I4: 22 000 + 0 - 18 000 | J4: Marcel Ronge | K4: Kája | L4: AAA, párce.cz, párce za rohem, jobdnes | M4: Refused offer: Kašpar, Hired: Svoboda (10.11.) For 2nd: Richtr, Kašpar, Láník (6.11.) Checking CVs | N4: 2 | O4: 0 | P4: 1
A5: NEW | B5: Brno | C5: 45947 | D5: 28 | E5: 179002 | F5: 05_Car Purchase | G5: Buying | H5: Test driver - Brno | I5: 22 000 + 0 - 18 000 | J5: Martin Kostelka | K5: Kamila | L5: AAA, prace.cz, pracezarohem, jobdnes | M5: To 2nd: Baláž (18.11.), to 2nd: Miksa, Žákovský (waiting for term) | N5: 10 | O5: 8 | P5: 3
A6: RPL (IM) | B6: ČESKÉ BUDĚJOVICE | C6: 45957 | D6: 18 | E6: 180119 | F6: 05_Car Purchase | G6: Buying | H6: Test driver - České Budějovice | I6: 22 000 + 0 - 18 000 | J6: Marcel Ronge | K6: Kája | L6: AAA, párce.cz, práce za rohem, jobdnes | M6: Checking CVs (IM - Jaroš, Ondrůšek) | N6: 5 | O6: 3 | P6: 1
A7: RPL (Kilián) | B7: Čestlice/Příbram | C7: 45971 | D7: 4 | E7: 179002 | F7: 05_Car Purchase | G7: Buying | H7: Test driver - Příbram | I7: 22 000 + 0 - 18 000 | J7: Lukáš Geršic | K7: Kamila | L7: AAA, prace.cz, pracezarohem, jobdnes | M7: new 1x IM (F.Hořínek ze Sokolova) | N7: 2 | O7: 0 | P7: 2
A8: RPL(fill cap) | B8: PRAGUE HQ / BO | C8: 45937 | D8: 38 | E8: 178528 | F8: 05_Car Purchase | G8: Mobile Buying | H8: Mobile Buying- České Budějovice | I8: 25000+% | J8: Tomáš Kaprálek | K8: Mirka | L8: AAA, práce.cz, jobs.cz, dobraprace, volnamista, jobdnes, pracezarohem | M8: Checking CVs No after 1st: Chlan | N8: 1 | O8: 1 | P8: 1
A9: (RPL Vargová - IM) | B9: PRAGUE HQ / BO | C9: 45959 | D9: 16 | E9: 179978 | F9: 05_Car Purchase | G9: Segment Buying | H9: Assistant | I9: negotiable | J9: Tomáš Preus | K9: Vlaďka | L9: Recommended | M9: rejected offer Videnková, After 1st
A10: RPL (Lukáš Vodák) | B10: PRAGUE HQ / BO | C10: 45931 | D10: 44 | E10: 180118 | F10: 05_Car Purchase | G10: Pricing | H10: Pricing Expert | I10: 30 000 + 0 - 10 000 VB (GB 3m) | J10: Jiří Somol | K10: Anna K. | L10: AAA, práce.cz, jobs.cz, dobraprace, volnamista, jobdnes | M10: For 2nd: Jungman (13.11.) Last h: Kříž Michal (1.10.), Dominik Burr (1.10.), Tejnický (2. 6.),Griessl (5.5.), Osagiede (1. 4.), Rudiš (3.3.) No after 2nd: Horák Ref.off: Vitouš | N10: 36 | O10: 35 | P10: 1

Sheet VACANCIES
A1: RPL / NEW | B1: Comment | C1: Place | D1: Date of opening | E1: Time to fill | F1: Request for position | G1: Division | H1: Department | I1: Position | J1: Salary | K1: Hiring Manager | L1: Generalist | M1: Sources | N1: Comments | O1: CAP | P1: ACTUAL | Q1: VAC
C2: Prague HQ / BO
A3: RPL | B3: fill cap | C3: Ostrava | D3: 46069 | E3: =_xlfn.DAYS(TODAY(),D3) -> 16 | G3: 11_Call Centre | H3: Call Centre | I3: CC Representative | J3: 22 500 + 0 - 7 500 (GB 1. a 2. měsíc, 3.+ %) | K3: Jan Kovář | L3: Anna K. | M3: AAA | N3: Hired: Bandurová, Jurek (16. 2.), Hiring: Horáková, Malíková (2.3.) No: Baláž | O3: 50.13 | P3: 45.1 | Q3: 5
A4: RPL | B4: Franková | C4: Prague HQ / BO | D4: 46069 | E4: =_xlfn.DAYS(TODAY(),D4) -> 16 | G4: 11_Call Centre | H4: Call Centre | I4: CC Representative | J4: 22 500 + 0 - 12 500 (1.+2. měsíc) 22 500 + % (od 3. měsíce) | K4: Vojta Toráč | L4: Kája | M4: AAA, práce za rohem, práce.cz | N4: Hired: Bino, Jusko (2.3.) Semecká- long term sickness | O4: 41 | P4: 42 | Q4: 0
A5: RPL | B5: Roubal | C5: Prague HQ / BO | D5: 46055 | E5: =_xlfn.DAYS(TODAY(),D5) -> 30 | F5: 182910 | G5: 08_Service | H5: Service | I5: Mechanic / Praha | J5: negotiable Ref. | K5: Miroslav Knap | L5: Honza | M5: AAA, jobdnes, dobrá práce, práce cz,inwork | N5: Checking CVs Hired Roubal (4.11.), Hensl (2.2.) | O5: 23 | P5: 21 | Q5: 2
A6: NEW | C6: Prague HQ / BO | D6: 45907 | E6: =_xlfn.DAYS(TODAY(),D6) -> 178 | F6: Waiting for RFP | G6: 08_Service | H6: Service | I6: Mechanic / České Budějovice | J6: negotiable Ref. | K6: Miroslav Knap | L6: Honza | M6: AAA, jobdnes, dobrá práce, práce cz,inwork | N6: IM Setikovský (1.3.) | O6: 2 | P6: 1 | Q6: 1
A7: RPL | B7: Daněk | C7: Brno | D7: 46076 | E7: =_xlfn.DAYS(TODAY(),D7) -> 9 | F7: 179250 | G7: 08_Service | H7: Service | I7: Mechanic / Brno | J7: negotiable Ref. | K7: Miroslav Knap | L7: Honza | M7: AAA, jobdnes, dobrá práce, práce cz,inwork | N7: new RQ | O7: 8 | P7: 7 | Q7: 1
A8: RPL | B8: Mikula | C8: Kladno | D8: 45956 | E8: =_xlfn.DAYS(TODAY(),D8) -> 129 | F8: 179250 | G8: 08_Service | H8: Service | I8: Mechanic / Kladno | J8: negotiable Ref. | K8: Miroslav Knap | L8: Honza | M8: AAA, jobdnes, dobrá práce, práce cz,inwork | N8: Checking CVs | O8: 1 | P8: 0 | Q8: 1
A9: RPL | B9: Kaštánek | C9: Prague HQ / BO | D9: 46038 | E9: =_xlfn.DAYS(TODAY(),D9) -> 47 | F9: Waiting for RFP | G9: 10_Office Operations | H9: Facility & Constuction | I9: Serviceman | J9: 30 000 + 0 - 8 000 KPI | K9: Petr Rinda | L9: Kamila | M9: Recommended | N9: hiring: Chalupecký (2.3.), refused offer: Babka | O9: 2 | P9: 2 | Q9: 1
A10: RPL | B10: Boušková | C10: Prague HQ / BO | D10: 46072 | E10: =_xlfn.DAYS(TODAY(),D10) -> 13 | F10: Waiting for RFP | G10: 10_Office Operations | H10: Warehouse & Archive | I10: Stockkeeper | J10: 30 000 + 0 - 9 000 KPI | K10: Ludvík Zawora | L10: Kamila | M10: AAA, práce cz, pracezarohem, inwork | N10: checking CVs | O10: 2 | P10: 2 | Q10: 1
A11: RPL | B11: Bartková/Varyš | C11: Prague HQ / BO | D11: 46072 | E11: =_xlfn.DAYS(TODAY(),D11) -> 13 | F11: Waiting for RFP | G11: 22_Cost Control & Back Office | H11: Cost Controlling & Procurement | I11: Procurement Specialist | J11: 43 000 + 0 - 10 000 KPI | K11: Michaela Kosinerová | L11: Kamila | M11: Recommended | N11: plánovaný IM | O11: 1.5 | P11: 0.5 | Q11: 1
A12: RPL | B12: fill cap, Šebánek, Černý | C12: Prague HQ / BO | D12: 46028 | E12: =_xlfn.DAYS(TODAY(),D12) -> 57 | F12: 176542 | G12: 07_Stock & Logistics | H12: Stock | I12: Stock Controller - Praha | J12: 25 000 + 0 - 25 000 KPI | K12: Borovec Josef | L12: Blanka | M12: AAA, práce.cz, pracezarohem, dobraprace | N12: Hiring Švarc After 2nd Butora, Cimburek No Afier 2nd Nouzák, Kolomazník Refused practise day Kulhánek Checking CV | O12: 7 | P12: 6 | Q12: 3
A13: RPL | B13: fill cap | C13: Liberec | D13: 46028 | E13: =_xlfn.DAYS(TODAY(),D13) -> 57 | F13: 176542 | G13: 07_Stock & Logistics | H13: Stock | I13: Stock Controller - Liberec | J13: 25 000 + 0 - 25 000 KPI | K13: Borovec Josef | L13: Blanka | M13: AAA, práce.cz, pracezarohem, dobraprace | N13: Hiring Saska (23.3.) No after 2nd Rejman Checking CV | O13: 2 | P13: 1 | Q13: 1
A14: RPL | B14: Setikovský | C14: Liberec | D14: 46049 | E14: =_xlfn.DAYS(TODAY(),D14) -> 36 | F14: 176542 | G14: 07_Stock & Logistics | H14: Stock | I14: Stock Controller - České Budějovice | J14: 25 000 + 0 - 25 000 KPI | K14: Borovec Josef | L14: Blanka | M14: AAA, práce.cz, pracezarohem, dobraprace | N14: Hiring Rotšédl (1.4.) No after 2nd Fomín Checking CVs | O14: 3 | P14: 3 | Q14: 1
A15: RPL | B15: fill cap | C15: Kladno | D15: 46077 | E15: =_xlfn.DAYS(TODAY(),D15) -> 8 | G15: 07_Stock & Logistics | H15: Stock | I15: Courier DPP - Kladno | J15: 140,-Kč//hod | K15: Jan Zvikl | L15: Mirka | M15: AAA, práce.cz, pracezarohem, dobraprace | N15: Checking CVs new request | O15: 0.25 | P15: 0 | Q15: 1
A16: RPL | B16: fill cap | C16: České Budějovice | D16: 46080 | E16: =_xlfn.DAYS(TODAY(),D16) -> 5 | G16: 07_Stock & Logistics | H16: Stock | I16: Courier DPP - České Budějovice | J16: 140,-Kč/hod. | K16: Jan Zvikl | L16: Mirka | M16: AAA, práce.cz, pracezarohem, dobraprace | N16: Checking CVs/new request | O16: 0.25 | P16: 0 | Q16: 1
A17: RPL | B17: Bryňák LTS, Kostiuk, Zlúky | C17: Prague HQ / BO | D17: 46084 | E17: =_xlfn.DAYS(TODAY(),D17) -> 1 | F17: 176542 | G17: 07_Stock & Logistics | H17: Logistics | I17: Tow Truck Driver - Praha | J17: 25 000 + 0 - 15 000 OSOH + 0 - 15 000 VB | K17: Alexandr Jordanov | L17: Mirka | M17: AAA, práce.cz, pracezarohem, dobraprace | N17: Hring: Hranáč (3.3) Hired: Zlúky (1.12)Ludvik(17.2) For 1st:Liška(19.2) For2nd: Hranáč(30.1) Refused offer:Jirovec, Brudny, Bartoň Dindnt comme: Macháček(13.10), Chromec | O17: 30 | P17: 30 | Q17: 2
A18: RPL | B18: Klejzar | C18: Prague HQ / BO | D18: 46048 | E18: =_xlfn.DAYS(TODAY(),D18) -> 37 | G18: 02_Car Sales | H18: Customer Care | I18: Customer Care Technician | J18: 35 000 + 0 - 11 000 KPI | K18: Žerebný Michal | L18: Blanka | M18: AAA, práce.cz, pracezarohem, dobraprace | N18: Hiring Vojta No after 2nd Mašek Checking CVs | O18: 3 | P18: 1.5 | Q18: 1
A19: RPL | C19: Prague HQ / BO | D19: 46028 | E19: =_xlfn.DAYS(TODAY(),D19) -> 57 | F19: 178528 | G19: 05_Car Purchase | H19: Mobile Buying | I19: Mobile Buying- Praha | J19: 25000+% | K19: Tomáš Kaprálek | L19: Mirka | M19: AAA, práce.cz, jobs.cz, dobraprace, volnamista, jobdnes, pracezarohem | N19: For 1nd: Kredba, Palyutin(10.2) After1st: Kredba, Palyutin(not suitable) Refused offer: Žižkovský | O19: 9 | P19: 9 | Q19: 1
A20: RPL | B20: Dobeš | C20: Prague HQ / BO | D20: 46035 | E20: =_xlfn.DAYS(TODAY(),D20) -> 50 | F20: 178528 | G20: 05_Car Purchase | H20: Mobile Buying | I20: Mobile Buying- Ostrava | J20: 25000+% | K20: Filip Lukašek | L20: Mirka | M20: AAA, práce.cz, jobs.cz, dobraprace, volnamista, jobdnes, pracezarohem | N20: After1st:Turay(not suitable) | O20: 1 | P20: 1 | Q20: 1
A21: RPL | B21: Zvěřinová | C21: Prague HQ / BO | D21: 46077 | E21: =_xlfn.DAYS(TODAY(),D21) -> 8 | F21: 178528 | G21: 05_Car Purchase | H21: Mobile Buying | I21: Mobile Buying Dispatcher Praha | J21: 25000+% | K21: Ondřej Holub | L21: Mirka | M21: AAA, práce.cz, jobs.cz, dobraprace, volnamista, jobdnes, pracezarohem | N21: Checking CVs/ new request | O21: 1 | P21: 1 | Q21: 1
C22: Mototechna
C23: Zličín
A24: NEW | B24: fill cap | C24: Zličín | D24: 46057 | E24: =_xlfn.DAYS(TODAY(),D24) -> 28 | G24: 04_Automotive OPS | H24: OPS (Part Time) | I24: Driver - Zličín | J24: 140 kč/Hod | K24: Jan Malchar | L24: Anna K. | M24: AAA | N24: Hired: Kočí (4.2), Blažka (4.2) For 2nd: Václavík (odloženo pro nemoc) | O24: 0.25 | P24: 0.25 | Q24: 3
B25: Reg. Praha | C25: Prague Branch
A26: RPL | B26: Dunda, Uher, fill cap | C26: Prague Branch | D26: 45919 | E26: =_xlfn.DAYS(TODAY(),D26) -> 166 | F26: 177091 178380 178368 180222 180494 | G26: 02_Car Sales | H26: Sales | I26: Salesman - Praha | J26: 25.000 + % | K26: Alen Svoboda | L26: Ondra | M26: AAA, práce, inwork | N26: For 2nd 2x Hired 16.2. Drahokoupil, 19.2. Humeník 2.3. Kótai Hired 12.1. Kamršek Hired for assistant 8.2. Dlabal Refused offer Kohák, Andrle No after 2nd 19x | O26: 36 | P26: 32 | Q26: 4
A27: RPL | B27: Král Josef | C27: Prague Branch | D27: 46008 | E27: =_xlfn.DAYS(TODAY(),D27) -> 77 | F27: 184212 | G27: 05_Car Purchase | H27: Buying | I27: Test driver - Praha | J27: 25 000 + 0 - 15 000 | K27: Petr Kuchynka | L27: Blanka | M27: AAA, prace.cz, pracezarohem, jobdnes | N27: Hiring Várady Hired Macháček (2.2.) No after 2nd Urban , Brož, Hubený Checking CV | O27: 20 | P27: 16 | Q27: 3
A28: RPL | C28: Prague Branch | D28: 46045 | E28: =_xlfn.DAYS(TODAY(),D28) -> 40 | G28: 05_Car Purchase | H28: Pricing CZ/SK/PL | I28: Pricing Expert | J28: 30 000 + 15 000 | K28: Jiří Somol | L28: Anna K. | M28: AAA, práce, inwork | N28: For1st: Hejduk (4.3) for 2nd int.: Kunst (25.2.) No: Dědek, Soustružník, Hlaváčková, Sivák, Bača | O28: 36.5 | P28: 33 | Q28: 1
A29: RPL | B29: Šimonová | C29: Prague Branch | D29: 46059 | E29: =_xlfn.DAYS(TODAY(),D29) -> 26 | G29: 05_Car Purchase | H29: Buying | I29: Receptionist | J29: 25 000 + 10 000 | K29: Petr Kuchynka | L29: Blanka | M29: AAA, prace.cz, pracezarohem, jobdnes | N29: Hiring Lisová (9.3.) Checking CVs | O29: 2 | P29: 2 | Q29: 1
A30: RPL | B30: Tomáš Kaiser | C30: Prague Branch | D30: 46054 | E30: =_xlfn.DAYS(TODAY(),D30) -> 31 | G30: 04_Automotive OPS | H30: OPS (Full Time) | I30: Helper - Praha | J30: 28 000 + 0 - 8 000 | K30: Jan Malchar | L30: Anna K. | M30: AAA, práce, inwork | N30: Roubal 1.2. No after 2nd: Slavík Švankmajer, Svoboda, Shten, Kalinov | O30: 26 | P30: 23 | Q30: 3
A31: RPL | B31: Jan Szabó | C31: Prague Branch | D31: 46062 | E31: =_xlfn.DAYS(TODAY(),D31) -> 23 | G31: 04_Automotive OPS | H31: OPS (Full Time) | I31: Helper Boxy a Sonax - Praha | J31: 28 000 + 0 - 8 000 | K31: Jan Malchar | L31: Anna K. | M31: AAA, práce, inwork | N31: Hired: Hangurbadžo (9.2.) Didnt come to the int: Peteřík 22.1., Vokulič (22.1) | O31: 4 | P31: 3 | Q31: 1
B32: Reg. Praha | C32: Čestlice
A33: RPL | B33: Šoltys | C33: Čestlice | D33: 45908 | E33: =_xlfn.DAYS(TODAY(),D33) -> 177 | F33: 176741 | G33: 02_Car Sales | H33: Selling | I33: Salesman - Čestlice | J33: 25.000 + 0 - 25.000 | K33: Alen Svoboda | L33: Ondra | M33: AAA, práce.cz, inwork, dobraprace | N33: Hired 2.3. Radčuk On hold Mládek Stopped hiring Reppenberger Checking CVs | O33: 4 | P33: 4 | Q33: 1
A34: RPL | B34: Hořínek | C34: Čestlice | D34: 46079 | E34: =_xlfn.DAYS(TODAY(),D34) -> 6 | F34: 179002 | G34: 05_Car Purchase | H34: Buying | I34: Test driver - Čestlice | J34: 25 000 + 0 - 15 000 | K34: Lukáš Geršic | L34: Kamila | M34: AAA, prace.cz, pracezarohem | N34: checking CVs | O34: 4 | P34: 4 | Q34: 1
A35: RPL | B35: Kilián | C35: Příbram | D35: 45971 | E35: =_xlfn.DAYS(TODAY(),D35) -> 114 | F35: 179002 | G35: 05_Car Purchase | H35: Buying | I35: Car Trader - Příbram | J35: 28 000 + 0 - 22 000 | K35: Lukáš Geršic | L35: Kamila | M35: AAA, prace.cz, pracezarohem | N35: In process: ex empl., To 2nd: Strama, Hochmann (waiting for term), No after 2nd: Říha, Niebauer, refused offer: Obdrdal, Vybíral 1x IM (F.Hořínek ze Sokolova) | O35: 2 | P35: 0 | Q35: 2
A36: RPL | B36: fill cap | C36: Čestlice | D36: 46055 | E36: =_xlfn.DAYS(TODAY(),D36) -> 30 | F36: DPP 2x | G36: 04_Automotive OPS | H36: OPS (Part Time) | I36: Driver - Čestlice | J36: 140 kč/Hod | K36: Jan Malchar | L36: Anna K. | M36: AAA, práce.cz, inwork, dobraprace | N36: Hired Hora (2.2.) No resp.: Čech, Kameník Vrbovec (17.10.), | O36: 0.25 | P36: 0.25 | Q36: 3
B37: Reg. Praha | C37: Klecany
J38: BRANCHES
B39: Bohemia 1 | C39: České Budějovice
A40: RPL | B40: fill cap | C40: České Budějovice | D40: 46028 | E40: =_xlfn.DAYS(TODAY(),D40) -> 57 | F40: 176834 | G40: 02_Car Sales | H40: Selling | I40: Salesman - České Budějovice 2 | J40: 25 000 + % | K40: Miroslav Varmuža | L40: Blanka | M40: AAA, práce, pracezarohem | N40: Hiring Vašák (2.3.) Hired Smutný (2.2.), Malý (16.2.) For 2nd Malý, Tyšler (next week) After 2nd Mužík, Volovenko Checking CV | O40: 8 | P40: 8 | Q40: 2
A41: RPL | B41: Tovačovský | C41: České Budějovice | D41: 46043 | E41: =_xlfn.DAYS(TODAY(),D41) -> 42 | F41: 184220 | G41: 03_Financial Services | H41: Selling Support | I41: Customer Service Specialist - České Budějovice | J41: 25 000 + % | K41: Andrea Habětínková | L41: Blanka | M41: AAA, práce.cz, inwork, dobraprace | N41: For 2nd Babic (next week) Checking CV | O41: 6 | P41: 6 | Q41: 1
A42: NEW | B42: NEW | C42: České Budějovice | D42: 46065 | E42: =_xlfn.DAYS(TODAY(),D42) -> 20 | F42: 178677 | G42: 04_Automotive OPS | H42: OPS | I42: Driver - České Budějovice | J42: 140 kč/hod | K42: Jan Sokola | L42: Kája | M42: AAA, jobdnes, práce cz | N42: For 2nd: Chmelař, Maxová Checking CV´s Zadán RQ na navýšení capu (2x) | O42: 1.75 | P42: 1.75 | Q42: 2
B43: Bohemia 1 | C43: Chomutov
A44: RPL | B44: Synek | C44: Chomutov | D44: 46057 | E44: =_xlfn.DAYS(TODAY(),D44) -> 28 | F44: 184220 | G44: 03_Financial Services | H44: Selling Support | I44: Customer Service Specialist - Chomutov | J44: 25 000 + % | K44: Andrea Habětínková | L44: Blanka | M44: AAA, práce.cz, inwork, dobraprace | N44: For 2nd Šafránková (3.3.) No after WT Rojt Checking CV | O44: 4 | P44: 4 | Q44: 1
A45: RPL | B45: Rohan, Panovský | C45: Chomutov | D45: 46029 | E45: =_xlfn.DAYS(TODAY(),D45) -> 56 | F45: 176834 | G45: 02_Car Sales | H45: Selling | I45: Salesman - Chomutov | J45: 25 000 + % | K45: Miroslav Varmuža | L45: Blanka | M45: AAA, práce, pracezarohem | N45: Hiring Demjan, Zelený (2.3.) Refused offer Kubovič Checking CV | O45: 4 | P45: 4 | Q45: 2
B46: Bohemia 1 | C46: Kladno
A47: RPL | B47: Trojan | C47: Kladno | D47: 46062 | E47: =_xlfn.DAYS(TODAY(),D47) -> 23 | G47: 04_Automotive OPS | H47: OPS | I47: Driver DPP Kladno | J47: 140,-Kč/hod. | K47: Čížek Martin | L47: Mirka | M47: AAA, práce za rohem, práce.cz | N47: Hiring: Žáčková (LP) For 1st: Procházka (4.3) Refused offer: Kolářová(18.2) | O47: 1.75 | P47: 1.25 | Q47: 1
B48: Bohemia 1 | C48: Plzeň
A49: RPL | B49: Riegerová | C49: Plzeň | D49: 46037 | E49: =_xlfn.DAYS(TODAY(),D49) -> 48 | F49: 184220 | G49: 03_Financial Services | H49: Selling Support | I49: Customer Service Specialist - Plzeň | J49: 25 000 + % | K49: Andrea Habětínková | L49: Blanka | M49: AAA, práce.cz, inwork, dobraprace | N49: Checking CV | O49: 6 | P49: 6 | Q49: 1
A50: RPL | B50: Korbel | C50: Plzeň | D50: 46071 | E50: =_xlfn.DAYS(TODAY(),D50) -> 14 | F50: 176834 | G50: 02_Car Sales | H50: Selling | I50: Salesman - Plzeň | J50: 25 000 + % | K50: Miroslav Varmuža | L50: Blanka | M50: AAA, práce, pracezarohem | N50: Didnt come Janíček Checking CV | O50: 7 | P50: 7 | Q50: 1
B51: Bohemia 1 | C51: Sokolov
A52: RPL | B52: fill cap | C52: Sokolov | D52: 46083 | E52: =_xlfn.DAYS(TODAY(),D52) -> 2 | F52: DPP | G52: 04_Automotive OPS | H52: OPS | I52: Driver DPP Sokolov | J52: 140,-Kč/hod | K52: Čížek Martin | L52: Mirka | M52: AAA, dobraprace, pracezarohem, práce cz | N52: Hired: Krejza(11.2), Matyáš (2.3) Hiring: Procházka(LP) After1st:Wnek(not suitable) | O52: 1.5 | P52: 1.5 | Q52: 2
A53: RPL | B53: fill cap, Mayer | C53: Sokolov | D53: 46055 | E53: =_xlfn.DAYS(TODAY(),D53) -> 30 | G53: 04_Automotive OPS | H53: OPS | I53: Helper - Sokolov | J53: 26 0000 + 0-6000 KPI | K53: Čížek Martin | L53: Blanka | M53: AAA, dobraprace, pracezarohem, práce cz | N53: Hiring Řáda No after 2nd Beníšek, Sys Checking CVs | O53: 8 | P53: 7 | Q53: 2
B54: Bohemia 1 | C54: Tábor
B55: Bohemia 2 | C55: Hradec Králové
A56: RPL | B56: ? | C56: Hradec Králové | D56: 46057 | E56: =_xlfn.DAYS(TODAY(),D56) -> 28 | F56: 178677 | G56: 02_Car Sales | H56: Selling | I56: Salesman - Hradec Králové | J56: 22 000 + % | K56: Petr Kalabis | L56: Kamila | M56: AAA, inwork, pracezarohem, práce cz | N56: Hiring: Chalupecký (15.3.), Practice day: Soska , To 2nd: Šimík (30.1.), No after 2nd: : Baťha, Hampl | O56: 6 | P56: 6 | Q56: 1
B57: Bohemia 2 | C57: Kolín
A58: RPL | B58: Kroužecká, Volencová | C58: Kolín | D58: 45691 | E58: =_xlfn.DAYS(TODAY(),D58) -> 394 | F58: 161947 | G58: 03_Financial Services | H58: Selling Support | I58: Customer Service Specialist - Kolín | J58: 25 000 + % Referral - 20 000 | K58: Martin Kotlán | L58: Kamila | M58: AAA, práce.cz, práce za rohem, jobs.cz | N58: Hiring: Pavlová (1.4.2026), No after 2nd: Drevenár, Kučerová, Pernicová, Havlík, Pachl, Batelková, Pichl, Kočerhán Refused offer: Krejčíková, Ben Rguez, Kolářová, Jirsa, Slavíčková, Talacko Didn´t come: Svobodová, Kumbera, Zadražil Hired: Volencová 3.2.2025 | O58: 4 | P58: 2 | Q58: 2
B59: Bohemia 2 | C59: Liberec
A60: RPL | B60: Tomášek, + ? | C60: Liberec | D60: 46055 | E60: =_xlfn.DAYS(TODAY(),D60) -> 30 | F60: 178677 | G60: 02_Car Sales | H60: Selling | I60: Salesman - Liberec | J60: 22 000 + % | K60: Petr Kalabis | L60: Kamila | M60: AAA, inwork, pracezarohem, práce cz | N60: Hiring: Michálek (2.3.), No after: Veselý, Schaffer | O60: 7 | P60: 8 | Q60: 1
A61: RPL | B61: Robová | C61: Liberec | D61: 46055 | E61: =_xlfn.DAYS(TODAY(),D61) -> 30 | F61: 161947 | G61: 03_Financial Services | H61: Selling Support | I61: Customer Service Specialist - Liberec | J61: 25 000 + % | K61: Martin Kotlán | L61: Kamila | M61: AAA, práce.cz, práce za rohem, jobs.cz | N61: No after practice day: Vidnerová | O61: 7.5 | P61: 7.25 | Q61: 1
A62: NEW | B62: fill cap | C62: Liberec | D62: 46065 | E62: =_xlfn.DAYS(TODAY(),D62) -> 20 | F62: DPP | G62: 04_Automotive OPS | H62: OPS | I62: Helper - Liberec | J62: 26 000 + 0-6 000 KPI | K62: Čížek Martin | L62: Kája | M62: AAA, jobdnes, pracezarohem, práce cz | N62: Hiring: Kropáč (9.3.), Hejduk (dle LP) No after 2nd: Baran, Břichňáč Refused offer: Palme Checking CV Zadán RQ na navýšení capu (1x) | O62: 10 | P62: 9 | Q62: 2
B63: Bohemia 2 | C63: Mladá Boleslav
A64: RPL | B64: Ryšavý | C64: Mladá Boleslav | D64: 46084 | E64: =_xlfn.DAYS(TODAY(),D64) -> 1 | F64: DPP | G64: 04_Automotive OPS | H64: OPS | I64: Helper - Mladá Boleslav | J64: 26 000 + 0-6 000 KPI | K64: Čížek Martin | L64: Kája | M64: AAA, dobraprace, pracezarohem, práce cz | N64: NEW | O64: 4 | P64: 3 | Q64: 1
B65: Bohemia 2 | C65: Teplice
A66: RPL | B66: Řeháková | C66: Teplice | D66: 46069 | E66: =_xlfn.DAYS(TODAY(),D66) -> 16 | F66: 161947 | G66: 03_Financial Services | H66: Selling Support | I66: Customer Service Specialist - Teplice | J66: 25 000 + % | K66: Martin Kotlán | L66: Kamila | M66: AAA, práce.cz, práce za rohem, jobs.cz | N66: Checking CVs | O66: 4 | P66: 4 | Q66: 1
A67: RPL | B67: Jeřábek, Hubert | C67: Teplice | D67: 46050 | E67: =_xlfn.DAYS(TODAY(),D67) -> 35 | F67: DPP | G67: 04_Automotive OPS | H67: OPS | I67: Helper - Teplice | J67: 26 000 + 0-6 000 KPI | K67: Čížek Martin | L67: Blanka | M67: AAA, dobraprace, pracezarohem, práce cz | N67: Hiring Novák, Parsch No after 2nd Cincibus, Vorasický, Vališ, Zacharda Checking CV | O67: 4 | P67: 4 | Q67: 2
A68: RPL | B68: fill cap | C68: Teplice | D68: 46055 | E68: =_xlfn.DAYS(TODAY(),D68) -> 30 | G68: 04_Automotive OPS | H68: OPS | I68: Driver DPP Teplice | J68: 140,-Kč/hod. | K68: Čížek Martin | L68: Mirka | M68: AAA, dobraprace, pracezarohem, práce cz | N68: Checking CV For1st: Mestl(23.2), Šidelka(25.2) | O68: 2 | P68: 2 | Q68: 3
B69: Bohemia 2 | C69: Ústí nad Labem
A70: RPL | B70: Valová | C70: Ústí nad Labem | D70: 46072 | E70: =_xlfn.DAYS(TODAY(),D70) -> 13 | F70: 161947 | G70: 03_Financial Services | H70: Selling Support | I70: Customer Service Specialist - Ústí | J70: 25 000 + % | K70: Martin Kotlán | L70: Kamila | M70: AAA, práce.cz, práce za rohem, jobs.cz | N70: Checking CVs | O70: 6 | P70: 6 | Q70: 1
A71: RPL | B71: Blahnik | C71: Ústí nad Labem | D71: 46055 | E71: =_xlfn.DAYS(TODAY(),D71) -> 30 | F71: 178677 | G71: 02_Car Sales | H71: Selling | I71: Salesman - Ústí nad Labem | J71: 22 000 + % | K71: Petr Kalabis | L71: Kamila | M71: AAA, dobraprace, inwork, pracezarohem, práce cz | N71: Hiring: Marek (3/2026) | O71: 4 | P71: 5 | Q71: 1
B72: Moravia 1 | C72: Brno
A73: RPL | C73: Brno | D73: 46059 | E73: =_xlfn.DAYS(TODAY(),D73) -> 26 | G73: 02_Car Sales | H73: Selling | I73: Salesman - Brno | J73: 25 000 + % | K73: Tomáš Krmela | L73: Ondra | M73: AAA, práce | N73: After 2nd 2x Hired 2.3. Pečinka | O73: 16 | P73: 16 | Q73: 1
A74: NEW CAP | C74: Brno | D74: 46059 | E74: =_xlfn.DAYS(TODAY(),D74) -> 26 | G74: 05_Car Purchase | H74: Selling | I74: Test Driver - Brno | J74: 25 000 + % | K74: Martin Kostelka | L74: Kamila | M74: AAA, práce, práce za rohem, Inwork | N74: checking CVs | O74: 14 | P74: 11 | Q74: 3
A75: RPL | B75: fill cap | C75: Brno | D75: 46063 | E75: =_xlfn.DAYS(TODAY(),D75) -> 22 | F75: 178677 | G75: 04_Automotive OPS | H75: OPS | I75: Helper - Brno | J75: 26 000 + 0 - 8 000 KPI | K75: Jan Sokola | L75: Kája | M75: AAA, dobraprace, pracezarohem, práce cz | N75: Hiring: Mejzlík (dle LP) After 2nd: Ptáček For 2nd: Boháček (??), Mach Didnt come: Komárek, Kučera Refused offer: Šíla Checking CV | O75: 18 | P75: 15 | Q75: 2
A76: RPL | B76: Tetur | C76: Brno | D76: 46076 | E76: =_xlfn.DAYS(TODAY(),D76) -> 9 | F76: 178677 | G76: 04_Automotive OPS | H76: OPS | I76: DPP Driver - Brno | J76: 140 Kč/hod | K76: Jan Sokola | L76: Kája | M76: AAA, dobraprace, pracezarohem, práce cz | N76: After 2nd: Rohrbacher (27.2.) Checking CV´s | O76: 3.5 | P76: 3 | Q76: 1
B77: Moravia 1 | C77: Jihlava
A78: RPL | B78: Škarvada | C78: Jihlava | D78: 46052 | E78: =_xlfn.DAYS(TODAY(),D78) -> 33 | G78: 02_Car Sales | H78: Selling | I78: Salesman - Jihlava | J78: 25 000 + % | K78: Tomáš Krmela | L78: Ondra | M78: AAA, prace.cz | N78: No after 2nd 3x Checking CVs | O78: 4 | P78: 4 | Q78: 1
A79: RPL | B79: fill cap | C79: Jihlava | D79: 46070 | E79: =_xlfn.DAYS(TODAY(),D79) -> 15 | F79: 178677 | G79: 04_Automotive OPS | H79: OPS | I79: Driver - Jihlava | J79: 140 Kč/hod | K79: Jan Sokola | L79: Kája | M79: AAA, dobraprace, pracezarohem, práce cz | N79: After 2nd: Pekárek (nezvedá tel) Refused offer: Janovský Hired: Pěnička (17.2.) | O79: 1.5 | P79: 1.15 | Q79: 1
B80: Moravia 1 | C80: Olomouc
A81: RPL | B81: Holub | C81: Olomouc | D81: 46078 | E81: =_xlfn.DAYS(TODAY(),D81) -> 7 | F81: DPP | G81: 04_Automotive OPS | H81: OPS | I81: Driver DPP Olomouc | J81: 125 Kč/hod | K81: Jan Sokola | L81: Mirka | M81: AAA, fajnbrigady, dobraprace, jobdnes | N81: Checking CV Hired: Zháněl(13.1), Vlášek (3.2), Esson (2.2), Sádecký(25.2) | O81: 1.25 | P81: 1.25 | Q81: 2
B82: Moravia 1 | C82: Znojmo
B83: Moravia 2 | C83: Opava
A84: RPL | B84: Motyčka | C84: Opava | D84: 46045 | E84: =_xlfn.DAYS(TODAY(),D84) -> 40 | G84: 02_Car Sales | H84: Salesman | I84: Salesman - Opava | J84: 25 000 + % | K84: Jiří Peška | L84: Anna K. | M84: AAA, práce, inwork | N84: for 3rd: Kohaut (20.2.) No after 2nd: Ščuka, Kurečka, Šafár, Hartel | O84: 3 | P84: 3 | Q84: 1
B85: Moravia 2 | C85: Ostrava
A86: RPL | B86: Vídeňský | C86: Ostrava | D86: 46055 | E86: =_xlfn.DAYS(TODAY(),D86) -> 30 | F86: 177033 | G86: 02_Car Sales | H86: Selling | I86: Salesman - Ostrava | J86: 25.000 + % | K86: Jiří Peška | L86: Anna K. | M86: AAA, práce, inwork | N86: Hiring: Bartošík (2.3.) Reffused offer Chylík, Zajíc, Kremser Hired Jonáš (2.2.) Červeň, Kromer (1.12.) No after 2nd: Hejl (assis), Kmeťo Didint come: Cmiel, Kamrád, Ulčák No after 2nd: Remeš | O86: 12.5 | P86: 11.5 | Q86: 1
A87: RPL | B87: Válový, Čermák | C87: Ostrava | D87: 46085 | E87: =_xlfn.DAYS(TODAY(),D87) -> 0 | G87: 04_Automotive OPS | H87: OPS | I87: Helper - Ostrava | J87: 26 000+0-6 000 KPI | K87: Jan Sokola | L87: Mirka | M87: AAA, dobraprace, prace.cz, pracezarohem | N87: Hiring: Hadravský (4.3) Refused offer: Hříva | O87: 16 | P87: 16 | Q87: 1
A88: RPL | B88: Michálek, Bonalsky | C88: Ostrava | D88: 46079 | E88: =_xlfn.DAYS(TODAY(),D88) -> 6 | G88: 04_Automotive OPS | H88: OPS | I88: Driver DPP Ostrava | J88: 140,-Kč/hod. | K88: Jan Sokola | L88: Mirka | M88: AAA, dobraprace, prace.cz, pracezarohem | N88: Hiring: Dulaj (LP) Hired: Milt (26.2) No after1st: Kukuča(6.2) | O88: 2.5 | P88: 2 | Q88: 3
B89: Moravia 2 | C89: Pardubice
A90: RPL | B90: Korbel | C90: Pardubice | D90: 46070 | E90: =_xlfn.DAYS(TODAY(),D90) -> 15 | G90: 02_Car Sales | H90: Selling | I90: Salesman - Pardubice | J90: 25.000 + % | K90: Jiří Peška | L90: Anna K. | M90: AAA, práce, inwork | N90: New request | O90: 4 | P90: 4 | Q90: 1
A91: RPL | B91: Prokop Dostál | C91: Pardubice | D91: 46065 | E91: =_xlfn.DAYS(TODAY(),D91) -> 20 | F91: waiting for RFP | G91: 04_Automotive OPS | H91: OPS | I91: Driver - Pardubice | J91: 140,-Kč/hod. | K91: Jan Sokola | L91: Kája | M91: AAA, prace.cz, práce za rohem, jobs | N91: Refused offer: Pavlík, Vitmar Checking CV´s | O91: 1.75 | P91: 1.5 | Q91: 1
B92: Moravia 2 | C92: Otrokovice
A93: RPL | B93: Matěj Novák | C93: Otrokovice | D93: 46027 | E93: =_xlfn.DAYS(TODAY(),D93) -> 58 | F93: 177092 | G93: 02_Car Sales | H93: Selling | I93: Salesman - Otrokovice | J93: 22.000 + % | K93: Jiří Peška | L93: Anna K. | M93: AAA, práce, inwork | N93: For 2nd: Pernický (20.2.)Reff. Off.: Dostál Hired: Jaroš (5. 1. 2026) | O93: 5 | P93: 5 | Q93: 1
A94: RPL | B94: fill cap | C94: Otrokovice | D94: 46084 | E94: =_xlfn.DAYS(TODAY(),D94) -> 1 | G94: 04_Automotive OPS | H94: OPS | I94: Driver DPP Otrokovice | J94: 140,-Kč/hod. | K94: Jan Sokola | L94: Mirka | M94: AAA, dobraprace, prace.cz, pracezarohem | N94: Hired: Halámek (3.3) Hiring: Straka (LP), Refused offer: Knot | O94: 1.75 | P94: 1 | Q94: 2
G160: 01_Marketing & Communication | Q160: 0
G161: 02_Car Sales | Q161: 0
G162: 03_Financial Services | Q162: 0
G163: 04_Automotive OPS | Q163: 0
G164: 05_Car Purchase | Q164: 0
G165: 06_HR | Q165: 0
...

Sheet Summary
A1: AAA AUTO — VACANCY SUMMARY REPORT
A2: CZ | Active Vacancies Overview
A4: KEY METRICS
A5: TOTAL POSITIONS | B5: =COUNTIF(VACANCIES!Q:Q,">0") -> 65
A7: TOTAL VACANCIES | B7: =SUMIFS(tblVacancies[VAC], tblVacancies[Division], "<>") -> 102
A9: TOTAL VACANCIES RPL | B9: =SUMIF(VACANCIES!A:A,"RPL*",VACANCIES!Q:Q) -> 91
A11: TOTAL VACANCIES NEW | B11: =SUMIF(VACANCIES!A:A,"NEW*",VACANCIES!Q:Q) -> 11
A13: Vac by Division | B13: Vacancies
A14: 02_Car Sales | B14: 20
A15: 03_Financial Services | B15: 8
A16: 04_Automotive OPS | B16: 38
A17: 05_Car Purchase | B17: 14
A18: 06_HR | B18: 0
A19: 07_Stock & Logistics | B19: 9
A20: 08_Service | B20: 5
A21: 11_Call Centre | B21: 5
A22: 12_IT | B22: 0
A23: 16_Mototechna | B23: 0
A24: 21_Commerce | B24: 0
A25: (prázdné)
A26: 22_Cost Control & Back Office | B26: 1
A27: 10_Office Operations | B27: 2
A28: 09_Economic | B28: 0
A29: 01_Marketing & Communication | B29: 0
A30: 18_Data Science | B30: 0
A31: 20_Innovations | B31: 0
A32: Celkový součet | B32: 102
A35: Vac by branch | B35: Vacancies
A36: Prague Branch | B36: 13
A37: Ostrava | B37: 10
A38: Brno | B38: 8
A39: Liberec | B39: 6
A40: Teplice | B40: 6
A41: České Budějovice | B41: 6
A42: Čestlice | B42: 5
A43: Sokolov | B43: 4
A44: Kladno | B44: 3
A45: Chomutov | B45: 3
A46: Otrokovice | B46: 3
A47: Kolín | B47: 2
... A55: Hradec Králové | B55: 1
A56: Znojmo
A57: Tábor
A58: Klecany
A59: Mototechna
A60: Celkový součet | B60: 82
A63: Vac by consultant | B63: Vacancies
A64: Blanka | B64: 22
A65: Mirka | B65: 21
A66: Anna K. | B66: 20
A67: Kamila | B67: 17
A68: Kája | B68: 10
A69: Ondra | B69: 7
A70: Honza | B70: 5
A71: Celkový součet | B71: 102
A73: Vac by hiring manager | B73: Vacancies
A74: Jan Sokola | B74: 15
A75: Čížek Martin | B75: 13
A76: Jan Malchar | B76: 10
A77: Jan Kovář | B77: 5
A78: Miroslav Knap | B78: 5
A79: Martin Kotlán | B79: 5
A80: Alen Svoboda | B80: 5
A81: Miroslav Varmuža | B81: 5
A82: Borovec Josef | B82: 5
A83: Jiří Peška | B83: 4
A84: Petr Kuchynka | B84: 4
A85: Andrea Habětínková | B85: 3
... A103: Celkový součet | B103: 102
A106: NARRATIVE SUMMARY ---- POKUS
A107: Aktuální stav (k 3. 3. 2026)
A108: Aktuálně se hledá celkem 103 volných míst (VAC) na 66 otevřených pozicích ve 22 lokalitách po celé ČR. Z toho 91 VAC jsou náhrady odcházejících zaměstnanců (RPL) a 11 VAC jsou nově vytvořené pozice (NEW).
A110: Nejhledanější pozice
A111: Nejvíce se hledají Salesmani (14 otevřených inzerátů, ~21 VAC), Řidiči / DPP Řidiči (10 inzerátů, ~20 VAC) a Helpeři (8 inzerátů, ~17 VAC). Tyto 3 typy pozic tvoří přes 55 % všech volných míst. Dalšími frekventovanými rolemi jsou Customer Service Specialist (7 inzerátů, 8 VAC) a Test Driver / Car Trader (5 inzerátů, 8 VAC).
A113: Nejproblematičtější pozice (vysoký Time to Fill)
A114: Nejdéle otevřená pozice je Customer Service Specialist v Kolíně — 393 dní, přes 15 odmítnutých kandidátů, obsazeni jen 2 ze 4. Jeden nástup naplánován na 1. 4. 2026 (Pavlová). Vyžaduje přehodnocení strategie (mzda, sourcing, referral). Další kritické případy: Salesman Čestlice (176 dní), Salesman Praha (165 dní), Mechanic Kladno (128 dní), Car Trader Příbram (113 dní).
A116: Divize a geografie
A117: Automotive OPS dominuje s 38 VAC (37 % celku) — převážně řidiči a helpeři. Následují Car Sales (20 VAC) a Car Purchase (14 VAC). Tyto 3 divize pokrývají 70 % náboru. Geograficky nejvytíženější lokality: Prague Branch (13 VAC), Ostrava (9), Brno (8), Liberec / Teplice / České Budějovice (po 6).
A119: Anomálie a upozornění
A120: 3 pozice mají ACTUAL > CAP: CC Representative Praha HQ (42/41), Salesman Liberec (8/7), Salesman Ústí nad Labem (5/4) — pravděpodobně čeká na schválení navýšení capu.
A121: Pozice Salesman Brno (Hired 2.3. Pečinka) a Driver Jihlava (Hired: Pěnička 17.2.) mají VAC=1, ale v komentářích je již uveden Hired s datem v minulosti — pozice pravděpodobně již obsazeny, VAC by mělo být aktualizováno.
... A138: • Office Cleaner DPP Otrokovice — Hiring: Václavíková (4.3.) — VAC 1 → pravděpodobně uzavřeno

Sheet Zdroj číselníků
A2: Anna K. | C2: RPL | E2: 01_Marketing & Communication
A3: Blanka | C3: NEW | E3: 02_Car Sales
A4: Honza | E4: 03_Financial Services
A5: Kája | E5: 04_Automotive OPS
A6: Kamila | E6: 05_Car Purchase
A7: Mirka | E7: 06_HR
A8: Ondra | E8: 07_Stock & Logistics
A9: Vlaďka | E9: 08_Service
E10: 09_Economic
E11: 10_Office Operations
E12: 11_Call Centre
E13: 12_IT
E14: 16_Mototechna
E15: 18_Data Science
E16: 20_Innovations
E17: 21_Commerce
E34: 22_Cost Control & Back Office
